Workbook
Name Slicer_averageRating: #N/A
Name Slicer_genres: #N/A
Name Slicer_numVotes: #N/A
Name Slicer_releaseYear: #N/A
Name Slicer_title: #N/A

Sheet Raw data
A1: id | B1: title | C1: genres | D1: averageRating | E1: numVotes | F1: releaseYear
A2: tt2322441 | B2: Fifty Shades of Grey | C2: Drama, Romance, Thriller | D2: 4.2 | E2: 341094 | F2: 2015
A3: tt1259571 | B3: The Twilight Saga: New Moon | C3: Adventure, Drama, Fantasy | D3: 4.8 | E3: 304888 | F3: 2009
A4: tt0118688 | B4: Batman & Robin | C4: Action, Sci-Fi | D4: 3.8 | E4: 272072 | F4: 1997
A5: tt6027920 | B5: The Iron Throne | C5: Action, Adventure, Drama | D5: 4 | E5: 267936 | F5: 2019
A6: tt1325004 | B6: The Twilight Saga: Eclipse | C6: Action, Adventure, Drama | D6: 5.1 | E6: 265386 | F6: 2010
A7: tt1324999 | B7: The Twilight Saga: Breaking Dawn - Part 1 | C7: Adventure, Drama, Fantasy | D7: 4.9 | E7: 258475 | F7: 2011
A8: tt0949731 | B8: The Happening | C8: Adventure, Drama, Sci-Fi | D8: 5 | E8: 220066 | F8: 2008
A9: tt1606378 | B9: A Good Day to Die Hard | C9: Action, Thriller | D9: 5.2 | E9: 217048 | F9: 2013
A10: tt1815862 | B10: After Earth | C10: Action, Adventure, Sci-Fi | D10: 4.8 | E10: 211275 | F10: 2013
A11: tt10857160 | B11: She-Hulk: Attorney at Law | C11: Action, Adventure, Comedy | D11: 5.2 | E11: 195388 | F11: 2022
A12: tt1628841 | B12: Independence Day: Resurgence | C12: Action, Adventure, Sci-Fi | D12: 5.2 | E12: 192018 | F12: 2016
A13: tt10888594 | B13: Radhe | C13: Action, Crime, Thriller | D13: 1.9 | E13: 180273 | F13: 2021
... A460: tt23900194 | B460: Harry & Meghan | C460: Biography, Documentary | D460: 5.1 | E460: 23649 | F460: 2022
A461: tt3835080 | B461: 31 | C461: Horror, Thriller | D461: 5.1 | E461: 23633 | F461: 2016
A462: tt4667094 | B462: Fifty Shades of Black | C462: Comedy | D462: 3.5 | E462: 23615 | F462: 2016
A463: tt0430770 | B463: The Women | C463: Comedy, Drama | D463: 5 | E463: 23466 | F463: 2008
A464: tt5322012 | B464: Wish Upon | C464: Drama, Fantasy, Horror | D464: 5.1 | E464: 23465 | F464: 2017
A465: tt2578802 | B465: Remember the Monsters? | C465: Crime, Drama, Mystery | D465: 4.8 | E465: 23460 | F465: 2013
A466: tt0360556 | B466: Fahrenheit 451 | C466: Drama, Sci-Fi, Thriller | D466: 5 | E466: 23421 | F466: 2018
A467: tt2974918 | B467: Alvin and the Chipmunks: The Road Chip | C467: Adventure, Comedy, Family | D467: 4.9 | E467: 23360 | F467: 2015
A468: tt15387022 | B468: Revenge/Justice | C468: Action, Adventure, Drama | D468: 5.1 | E468: 23343 | F468: 2024
A469: tt12783454 | B469: The Kissing Booth 3 | C469: Comedy, Romance | D469: 4.8 | E469: 23297 | F469: 2021
A470: tt1373215 | B470: Recep Ivedik 2 | C470: Comedy | D470: 4.5 | E470: 23286 | F470: 2009
A471: tt6950476 | B471: Tejas | C471: Action, Drama, Thriller | D471: 4.4 | E471: 23267 | F471: 2023
A472: tt5997666 | B472: Jab Harry Met Sejal | C472: Comedy, Drama, Romance | D472: 5.1 | E472: 23205 | F472: 2017
A473: tt6910020 | B473: Nothing to Lose | C473: Biography, Drama | D473: 2.4 | E473: 23140 | F473: 2018
... A784: tt15387058 | B784: Choice | C784: Action, Adventure, Drama | D784: 4.6 | E784: 12654 | F784: 2024
A785: tt1712159 | B785: 40858 | C785: Horror, Mystery, Thriller | D785: 3.9 | E785: 12653 | F785: 2011
A786: tt2091478 | B786: Air | C786: Drama, Sci-Fi, Thriller | D786: 5.1 | E786: 12651 | F786: 2015
A787: tt0110647 | B787: The NeverEnding Story III | C787: Adventure, Comedy, Family | D787: 3.2 | E787: 12633 | F787: 1994
A788: tt3053228 | B788: Day of the Dead: Bloodline | C788: Action, Drama, Horror | D788: 3.5 | E788: 12616 | F788: 2017
A789: tt0089280 | B789: Hobgoblins | C789: Comedy, Horror, Sci-Fi | D789: 2.2 | E789: 12606 | F789: 1988
A790: tt1403988 | B790: The Romantics | C790: Comedy, Drama, Romance | D790: 5 | E790: 12596 | F790: 2010
A791: tt5884234 | B791: First Kill | C791: Action, Thriller | D791: 5 | E791: 12582 | F791: 2017
A792: tt1780762 | B792: Aftershock | C792: Action, Adventure, Horror | D792: 4.8 | E792: 12573 | F792: 2012
A793: tt1552211 | B793: The Last Days of American Crime | C793: Action, Crime, Drama | D793: 3.8 | E793: 12566 | F793: 2020
A794: tt0462395 | B794: Larry the Cable Guy: Health Inspector | C794: Comedy, Romance | D794: 3.5 | E794: 12561 | F794: 2006
A795: tt3322892 | B795: XX | C795: Horror | D795: 4.6 | E795: 12545 | F795: 2017
A796: tt0118539 | B796: 3 Ninjas: High Noon at Mega Mountain | C796: Action, Adventure, Comedy | D796: 3 | E796: 12537 | F796: 1998
A797: tt0476958 | B797: Amusement | C797: Crime, Horror, Mystery | D797: 4.9 | E797: 12525 | F797: 2008
... A830: tt2292959 | B830: The Canyons | C830: Drama, Thriller | D830: 3.8 | E830: 12096 | F830: 2013
A831: tt1918734 | B831: 2067 | C831: Mystery, Sci-Fi | D831: 4.9 | E831: 12090 | F831: 2020
A832: tt10303324 | B832: Survive the Night | C832: Action, Drama, Thriller | D832: 4 | E832: 12082 | F832: 2020
A833: tt1619880 | B833: Sharktopus | C833: Action, Adventure, Comedy | D833: 3.2 | E833: 12070 | F833: 2010
A834: tt14813212 | B834: The Munsters | C834: Comedy, Family, Fantasy | D834: 4.5 | E834: 12066 | F834: 2022
A835: tt6210996 | B835: 10x10 | C835: Drama, Mystery, Thriller | D835: 5.1 | E835: 12066 | F835: 2018
A836: tt13429362 | B836: In the Earth | C836: Drama, Horror, Mystery | D836: 5.1 | E836: 12061 | F836: 2021
A837: tt9625664 | B837: Trauma Center | C837: Action, Thriller | D837: 4 | E837: 12059 | F837: 2019
A838: tt0092115 | B838: Troll | C838: Comedy, Fantasy, Horror | D838: 4.6 | E838: 12050 | F838: 1986
A839: tt21403988 | B839: The Last Pharaoh | C839: Documentary, Drama, History | D839: 1.1 | E839: 12019 | F839: 2023
A840: tt3038708 | B840: Iron Sky: The Coming Race | C840: Action, Adventure, Comedy | D840: 5 | E840: 12014 | F840: 2019
A841: tt4419364 | B841: Holidays | C841: Fantasy, Horror, Mystery | D841: 5.1 | E841: 12010 | F841: 2016
A842: tt0787505 | B842: Rest Stop | C842: Horror, Romance, Thriller | D842: 4.5 | E842: 11963 | F842: 2006
A843: tt6843812 | B843: Baaghi 2 | C843: Action, Crime, Drama | D843: 4.8 | E843: 11945 | F843: 2018
... A1001: tt4651410 | B1001: Precious Cargo | C1001: Action, Comedy, Thriller | D1001: 4.6 | E1001: 10007 | F1001: 2016

Sheet INDEX
B3: CHAPTERS | C3: FUNCTIONS USED
B4: 1 | C4: SUM, AVERAGE, MIN, MAX, COUNT, COUNTA
B5: 2 | C5: RANK.EQ, AVERAGEIF, COUNT IF, SUM IF,LARGE, SMALL,STANDARD DEVIATION, MEDIAN,MODE
B6: 3 | C6: COUNTIF, SUMIFS,ROUND
B7: 3.1 | C7: STOCKS(OPEN, VOLUME, HIGH LOW CHARTS)
B8: 4 | C8: CONDITIONAL FORMATTING, IF, OR, AND, NOT
B9: 5 | C9: VLOOKUP, UNIQUE, COUNTIF, SUMIFS, INDEX MATCH
B10: 6 | C10: IPMT, PPMT
B11: 7 | C11: SLICERS, CONCAT,TRIM
B12: 7.1 | C12: PIVOT TABLES
B13: 8 | C13: BREAK EVEN ANALYSIS, DATA TABLE
B14: 9 | C14: GOAL SEEK

Sheet Chapter - 1
A1: id | B1: title | C1: genres | D1: averageRating | E1: numVotes | F1: releaseYear
A2: tt2322441 | B2: Fifty Shades of Grey | C2: Drama, Romance, Thriller | D2: 4.2 | E2: 341094 | F2: 2015 | H2: Chapter 1: Basic Formula's
A3: tt1259571 | B3: The Twilight Saga: New Moon | C3: Adventure, Drama, Fantasy | D3: 4.8 | E3: 304888 | F3: 2009 | H3: Sum | I3: Total Numbe of Votes | J3: =SUM(E2:E1001) -> 34265064
A4: tt0118688 | B4: Batman & Robin | C4: Action, Sci-Fi | D4: 3.8 | E4: 272072 | F4: 1997 | H4: Average | I4: Average of NumVotes | J4: =AVERAGE(E2:E1001) -> 34265.064
A5: tt6027920 | B5: The Iron Throne | C5: Action, Adventure, Drama | D5: 4 | E5: 267936 | F5: 2019 | H5: Minimum | I5: Minimum Rating | J5: =MIN(D2:D1001) -> 1
A6: tt1325004 | B6: The Twilight Saga: Eclipse | C6: Action, Adventure, Drama | D6: 5.1 | E6: 265386 | F6: 2010 | H6: Mximum | I6: Maximum Rating | J6: =MAX(D2:D1001) -> 5.2
A7: tt1324999 | B7: The Twilight Saga: Breaking Dawn - Part 1 | C7: Adventure, Drama, Fantasy | D7: 4.9 | E7: 258475 | F7: 2011 | H7: Count | I7: ReleaseYear | J7: =COUNT(F2:F1001) -> 1000
A8: tt0949731 | B8: The Happening | C8: Adventure, Drama, Sci-Fi | D8: 5 | E8: 220066 | F8: 2008 | H8: CountA | I8: Title | J8: =COUNTA(B2:B1001) -> 1000
A9: tt1606378 | B9: A Good Day to Die Hard | C9: Action, Thriller | D9: 5.2 | E9: 217048 | F9: 2013
A10: tt1815862 | B10: After Earth | C10: Action, Adventure, Sci-Fi | D10: 4.8 | E10: 211275 | F10: 2013
A11: tt10857160 | B11: She-Hulk: Attorney at Law | C11: Action, Adventure, Comedy | D11: 5.2 | E11: 195388 | F11: 2022
A12: tt1628841 | B12: Independence Day: Resurgence | C12: Action, Adventure, Sci-Fi | D12: 5.2 | E12: 192018 | F12: 2016
A13: tt10888594 | B13: Radhe | C13: Action, Crime, Thriller | D13: 1.9 | E13: 180273 | F13: 2021
A14: tt1502712 | B14: Fantastic Four | C14: Action, Adventure, Sci-Fi | D14: 4.3 | E14: 179961 | F14: 2015
A15: tt0938283 | B15: The Last Airbender | C15: Action, Adventure, Family | D15: 4 | E15: 176827 | F15: 2010
A16: tt0859163 | B16: The Mummy: Tomb of the Dragon Emperor | C16: Action, Adventure, Fantasy | D16: 5.2 | E16: 173199 | F16: 2008
A17: tt3371366 | B17: Transformers: The Last Knight | C17: Action, Adventure, Sci-Fi | D17: 5.2 | E17: 172818 | F17: 2017
A18: tt0120891 | B18: Wild Wild West | C18: Action, Comedy, Sci-Fi | D18: 4.9 | E18: 168977 | F18: 1999
A19: tt5433138 | B19: F9: The Fast Saga | C19: Action, Crime, Thriller | D19: 5.2 | E19: 166852 | F19: 2021
A20: tt5108870 | B20: Morbius | C20: Action, Adventure, Horror | D20: 5.1 | E20: 158856 | F20: 2022
... A460: tt23900194 | B460: Harry & Meghan | C460: Biography, Documentary | D460: 5.1 | E460: 23649 | F460: 2022
A461: tt3835080 | B461: 31 | C461: Horror, Thriller | D461: 5.1 | E461: 23633 | F461: 2016
A462: tt4667094 | B462: Fifty Shades of Black | C462: Comedy | D462: 3.5 | E462: 23615 | F462: 2016
A463: tt0430770 | B463: The Women | C463: Comedy, Drama | D463: 5 | E463: 23466 | F463: 2008
A464: tt5322012 | B464: Wish Upon | C464: Drama, Fantasy, Horror | D464: 5.1 | E464: 23465 | F464: 2017
A465: tt2578802 | B465: Remember the Monsters? | C465: Crime, Drama, Mystery | D465: 4.8 | E465: 23460 | F465: 2013
A466: tt0360556 | B466: Fahrenheit 451 | C466: Drama, Sci-Fi, Thriller | D466: 5 | E466: 23421 | F466: 2018
A467: tt2974918 | B467: Alvin and the Chipmunks: The Road Chip | C467: Adventure, Comedy, Family | D467: 4.9 | E467: 23360 | F467: 2015
A468: tt15387022 | B468: Revenge/Justice | C468: Action, Adventure, Drama | D468: 5.1 | E468: 23343 | F468: 2024
A469: tt12783454 | B469: The Kissing Booth 3 | C469: Comedy, Romance | D469: 4.8 | E469: 23297 | F469: 2021
A470: tt1373215 | B470: Recep Ivedik 2 | C470: Comedy | D470: 4.5 | E470: 23286 | F470: 2009
A471: tt6950476 | B471: Tejas | C471: Action, Drama, Thriller | D471: 4.4 | E471: 23267 | F471: 2023
A472: tt5997666 | B472: Jab Harry Met Sejal | C472: Comedy, Drama, Romance | D472: 5.1 | E472: 23205 | F472: 2017
A473: tt6910020 | B473: Nothing to Lose | C473: Biography, Drama | D473: 2.4 | E473: 23140 | F473: 2018
... A784: tt15387058 | B784: Choice | C784: Action, Adventure, Drama | D784: 4.6 | E784: 12654 | F784: 2024
A785: tt1712159 | B785: 40858 | C785: Horror, Mystery, Thriller | D785: 3.9 | E785: 12653 | F785: 2011
A786: tt2091478 | B786: Air | C786: Drama, Sci-Fi, Thriller | D786: 5.1 | E786: 12651 | F786: 2015
A787: tt0110647 | B787: The NeverEnding Story III | C787: Adventure, Comedy, Family | D787: 3.2 | E787: 12633 | F787: 1994
A788: tt3053228 | B788: Day of the Dead: Bloodline | C788: Action, Drama, Horror | D788: 3.5 | E788: 12616 | F788: 2017
A789: tt0089280 | B789: Hobgoblins | C789: Comedy, Horror, Sci-Fi | D789: 2.2 | E789: 12606 | F789: 1988
A790: tt1403988 | B790: The Romantics | C790: Comedy, Drama, Romance | D790: 5 | E790: 12596 | F790: 2010
A791: tt5884234 | B791: First Kill | C791: Action, Thriller | D791: 5 | E791: 12582 | F791: 2017
A792: tt1780762 | B792: Aftershock | C792: Action, Adventure, Horror | D792: 4.8 | E792: 12573 | F792: 2012
A793: tt1552211 | B793: The Last Days of American Crime | C793: Action, Crime, Drama | D793: 3.8 | E793: 12566 | F793: 2020
A794: tt0462395 | B794: Larry the Cable Guy: Health Inspector | C794: Comedy, Romance | D794: 3.5 | E794: 12561 | F794: 2006
A795: tt3322892 | B795: XX | C795: Horror | D795: 4.6 | E795: 12545 | F795: 2017
A796: tt0118539 | B796: 3 Ninjas: High Noon at Mega Mountain | C796: Action, Adventure, Comedy | D796: 3 | E796: 12537 | F796: 1998
A797: tt0476958 | B797: Amusement | C797: Crime, Horror, Mystery | D797: 4.9 | E797: 12525 | F797: 2008
... A830: tt2292959 | B830: The Canyons | C830: Drama, Thriller | D830: 3.8 | E830: 12096 | F830: 2013
A831: tt1918734 | B831: 2067 | C831: Mystery, Sci-Fi | D831: 4.9 | E831: 12090 | F831: 2020
A832: tt10303324 | B832: Survive the Night | C832: Action, Drama, Thriller | D832: 4 | E832: 12082 | F832: 2020
A833: tt1619880 | B833: Sharktopus | C833: Action, Adventure, Comedy | D833: 3.2 | E833: 12070 | F833: 2010
A834: tt14813212 | B834: The Munsters | C834: Comedy, Family, Fantasy | D834: 4.5 | E834: 12066 | F834: 2022
A835: tt6210996 | B835: 10x10 | C835: Drama, Mystery, Thriller | D835: 5.1 | E835: 12066 | F835: 2018
A836: tt13429362 | B836: In the Earth | C836: Drama, Horror, Mystery | D836: 5.1 | E836: 12061 | F836: 2021
A837: tt9625664 | B837: Trauma Center | C837: Action, Thriller | D837: 4 | E837: 12059 | F837: 2019
A838: tt0092115 | B838: Troll | C838: Comedy, Fantasy, Horror | D838: 4.6 | E838: 12050 | F838: 1986
A839: tt21403988 | B839: The Last Pharaoh | C839: Documentary, Drama, History | D839: 1.1 | E839: 12019 | F839: 2023
A840: tt3038708 | B840: Iron Sky: The Coming Race | C840: Action, Adventure, Comedy | D840: 5 | E840: 12014 | F840: 2019
A841: tt4419364 | B841: Holidays | C841: Fantasy, Horror, Mystery | D841: 5.1 | E841: 12010 | F841: 2016
A842: tt0787505 | B842: Rest Stop | C842: Horror, Romance, Thriller | D842: 4.5 | E842: 11963 | F842: 2006
A843: tt6843812 | B843: Baaghi 2 | C843: Action, Crime, Drama | D843: 4.8 | E843: 11945 | F843: 2018
... A1001: tt4651410 | B1001: Precious Cargo | C1001: Action, Comedy, Thriller | D1001: 4.6 | E1001: 10007 | F1001: 2016

Sheet Chapter - 2
A1: title | B1: genres | C1: averageRating | D1: Ranking on AvgRating | E1: numVotes | F1: releaseYear
A2: Under Paris | B2: Action, Drama, Horror | C2: 5.2 | D2: =_xlfn.RANK.EQ(C2, C2:C1001) -> 1 | E2: 32479 | F2: 2024
A3: Uglies | B3: Action, Adventure, Drama | C3: 4.7 | D3: =_xlfn.RANK.EQ(C3, C3:C1002) -> 423 | E3: 25779 | F3: 2024 | H3: Chapter 2: Basic Formula's
A4: Trigger Warning | B4: Action, Crime, Thriller | C4: 4.6 | D4: =_xlfn.RANK.EQ(C4, C4:C1003) -> 498 | E4: 17570 | F4: 2024 | H4: AVERAGEIF | I4: Average rating for movies in "Action" genre | J4: =AVERAGEIF(B2:B1001, "Action", C2:C1001) -> 4.25
A5: The Tearsmith | B5: Drama, Fantasy, Romance | C5: 5.1 | D5: =_xlfn.RANK.EQ(C5, C5:C1004) -> 48 | E5: 10227 | F5: 2024 | H5: SUMIF | I5: Sum of numVotes for movies with averageRating > 5.1 | J5: =SUMIF(C2:C1001, ">5.1", E2:E1001) -> 3767189
A6: The Strangers: Chapter 1 | B6: Horror | C6: 4.6 | D6: =_xlfn.RANK.EQ(C6, C6:C1005) -> 497 | E6: 19176 | F6: 2024 | H6: MEDIAN | I6: AverageRating | J6: =MEDIAN(C2:C1001) -> 4.6
A7: The Platform 2 | B7: Horror, Sci-Fi, Thriller | C7: 5 | D7: =_xlfn.RANK.EQ(C7, C7:C1006) -> 170 | E7: 29234 | F7: 2024 | H7: MODE | I7: AverageRating | J7: =MODE(C2:C1001) -> 5.1
A8: The Deliverance | B8: Horror, Thriller | C8: 5.1 | D8: =_xlfn.RANK.EQ(C8, C8:C1007) -> 48 | E8: 19367 | F8: 2024 | H8: STANDARD DEVIATION | I8: AverageRating | J8: =STDEV( C2:C1001) -> 0.89266525
A9: The Crow | B9: Action, Crime, Fantasy | C9: 4.7 | D9: =_xlfn.RANK.EQ(C9, C9:C1008) -> 420 | E9: 24427 | F9: 2024 | H9: COUNTIF | I9: Movies with averageRating > 4.4 | J9: =COUNTIF(C2:C1001, ">4.4") -> 610
A10: The American Society of Magical Negroes | B10: Comedy, Fantasy | C10: 3.6 | D10: =_xlfn.RANK.EQ(C10, C10:C1009) -> 820 | E10: 10937 | F10: 2024 | H10: COUNTIFS | I10: Movies with averageRating > 4.4 and numVotes > 20,000 | J10: =COUNTIFS(C2:C1001, ">4.4", E2:E1001, ">20000") -> 343
A11: The Acolyte | B11: Action, Adventure, Drama | C11: 4.1 | D11: =_xlfn.RANK.EQ(C11, C11:C1010) -> 714 | E11: 124735 | F11: 2024 | H11: LARGE | I11: 1st largest value in the numVotes column | J11: =LARGE(E2:E1001, 1) -> 341094
A12: Teach/Corrupt | B12: Action, Adventure, Drama | C12: 5.1 | D12: =_xlfn.RANK.EQ(C12, C12:C1011) -> 48 | E12: 12964 | F12: 2024 | H12: LARGE | I12: 2nd largest value in the numVotes column | J12: =LARGE(E2:E1001, 2) -> 304888
A13: Tarot | B13: Horror | C13: 4.8 | D13: =_xlfn.RANK.EQ(C13, C13:C1012) -> 324 | E13: 25522 | F13: 2024 | H13: SMALL | I13: 1st smallest value in the averageRating column | J13: =SMALL(E2:E1001, 1) -> 10007
A14: Revenge/Justice | B14: Action, Adventure, Drama | C14: 5.1 | D14: =_xlfn.RANK.EQ(C14, C14:C1013) -> 48 | E14: 23343 | F14: 2024 | H14: SMALL | I14: 2nd smallest value in the averageRating column | J14: =SMALL(E2:E1001, 2) -> 10015
A15: Now or Never! | B15: Adventure, Biography, Drama | C15: 2 | D15: =_xlfn.RANK.EQ(C15, C15:C1014) -> 947 | E15: 16400 | F15: 2024
A16: Night Swim | B16: Horror, Thriller | C16: 4.7 | D16: =_xlfn.RANK.EQ(C16, C16:C1015) -> 417 | E16: 25006 | F16: 2024 | H16: How many titles are there in a releaseYear and averageRating of each title
A17: Mother of the Bride | B17: Comedy, Drama, Romance | C17: 4.8 | D17: =_xlfn.RANK.EQ(C17, C17:C1016) -> 323 | E17: 15187 | F17: 2024 | H17: Release Year | I17: Count of Titles in the Year 2015 - 2024 | J17: Average Rating
A18: Megalopolis | B18: Drama, Fantasy, Sci-Fi | C18: 5.1 | D18: =_xlfn.RANK.EQ(C18, C18:C1017) -> 48 | E18: 17457 | F18: 2024 | H18: 2015 | I18: =COUNTIF(F:F, H18) -> 35 | J18: =ROUND(AVERAGEIF(F:F, H18, C:C), 1) -> 4.4
A19: Martin | B19: Action, Drama, Thriller | C19: 4.5 | D19: =_xlfn.RANK.EQ(C19, C19:C1018) -> 551 | E19: 34529 | F19: 2024 | H19: 2016 | I19: =COUNTIF(F:F, H19) -> 29 | J19: =ROUND(AVERAGEIF(F:F, H19, C:C), 1) -> 4.5
A20: Madame Web | B20: Action, Adventure, Sci-Fi | C20: 4 | D20: =_xlfn.RANK.EQ(C20, C20:C1019) -> 728 | E20: 91349 | F20: 2024 | H20: 2017 | I20: =COUNTIF(F:F, H20) -> 39 | J20: =ROUND(AVERAGEIF(F:F, H20, C:C), 1) -> 4.3
A21: Indian Police Force | B21: Action, Crime, Drama | C21: 4.9 | D21: =_xlfn.RANK.EQ(C21, C21:C1020) -> 248 | E21: 58338 | F21: 2024 | H21: 2018 | I21: =COUNTIF(F:F, H21) -> 37 | J21: =ROUND(AVERAGEIF(F:F, H21, C:C), 1) -> 4.2
A22: Indian 2 | B22: Action, Drama, Thriller | C22: 3.9 | D22: =_xlfn.RANK.EQ(C22, C22:C1021) -> 747 | E22: 15666 | F22: 2024 | H22: 2019 | I22: =COUNTIF(F:F, H22) -> 37 | J22: =ROUND(AVERAGEIF(F:F, H22, C:C), 1) -> 4.2
A23: Imaginary | B23: Horror, Mystery, Thriller | C23: 4.7 | D23: =_xlfn.RANK.EQ(C23, C23:C1022) -> 414 | E23: 15023 | F23: 2024 | H23: 2020 | I23: =COUNTIF(F:F, H23) -> 47 | J23: =ROUND(AVERAGEIF(F:F, H23, C:C), 1) -> 4.1
A24: Destiny | B24: Action, Adventure, Drama | C24: 3.7 | D24: =_xlfn.RANK.EQ(C24, C24:C1023) -> 793 | E24: 25920 | F24: 2024 | H24: 2021 | I24: =COUNTIF(F:F, H24) -> 41 | J24: =ROUND(AVERAGEIF(F:F, H24, C:C), 1) -> 4.1
A25: Day | B25: Action, Adventure, Drama | C25: 4.8 | D25: =_xlfn.RANK.EQ(C25, C25:C1024) -> 321 | E25: 17929 | F25: 2024 | H25: 2022 | I25: =COUNTIF(F:F, H25) -> 46 | J25: =ROUND(AVERAGEIF(F:F, H25, C:C), 1) -> 4.2
A26: Choice | B26: Action, Adventure, Drama | C26: 4.6 | D26: =_xlfn.RANK.EQ(C26, C26:C1025) -> 485 | E26: 12654 | F26: 2024 | H26: 2023 | I26: =COUNTIF(F:F, H26) -> 33 | J26: =ROUND(AVERAGEIF(F:F, H26, C:C), 1) -> 4
A27: Borderlands | B27: Action, Adventure, Comedy | C27: 4.6 | D27: =_xlfn.RANK.EQ(C27, C27:C1026) -> 485 | E27: 31263 | F27: 2024 | H27: 2024 | I27: =COUNTIF(F:F, H27) -> 29 | J27: =ROUND(AVERAGEIF(F:F, H27, C:C), 1) -> 4.5
A28: Bhool Bhulaiyaa 3 | B28: Comedy, Horror | C28: 5 | D28: =_xlfn.RANK.EQ(C28, C28:C1027) -> 166 | E28: 30918 | F28: 2024
A29: Bade Miyan Chote Miyan | B29: Action, Adventure, Sci-Fi | C29: 3.9 | D29: =_xlfn.RANK.EQ(C29, C29:C1028) -> 742 | E29: 38451 | F29: 2024
A30: Bad Newz | B30: Comedy, Romance | C30: 4.9 | D30: =_xlfn.RANK.EQ(C30, C30:C1029) -> 247 | E30: 25175 | F30: 2024
A31: Yaariyan 2 | B31: Comedy, Drama, Musical | C31: 5.1 | D31: =_xlfn.RANK.EQ(C31, C31:C1030) -> 48 | E31: 11639 | F31: 2023
A32: Winnie-the-Pooh: Blood and Honey | B32: Horror | C32: 2.9 | D32: =_xlfn.RANK.EQ(C32, C32:C1031) -> 879 | E32: 31766 | F32: 2023
A33: Velma | B33: Adventure, Animation, Comedy | C33: 1.6 | D33: =_xlfn.RANK.EQ(C33, C33:C1032) -> 947 | E33: 79558 | F33: 2023
A34: The Strays | B34: Drama, Mystery, Thriller | C34: 4.9 | D34: =_xlfn.RANK.EQ(C34, C34:C1033) -> 246 | E34: 12479 | F34: 2023
A35: The Last Pharaoh | B35: Documentary, Drama, History | C35: 1.1 | D35: =_xlfn.RANK.EQ(C35, C35:C1034) -> 962 | E35: 12019 | F35: 2023
A36: The Idol | B36: Drama, Music | C36: 4.4 | D36: =_xlfn.RANK.EQ(C36, C36:C1035) -> 587 | E36: 112636 | F36: 2023
A37: The Holy Trinity | B37: Horror | C37: 3.2 | D37: =_xlfn.RANK.EQ(C37, C37:C1036) -> 854 | E37: 12288 | F37: 2023
A38: The Expendables 4 | B38: Action, Adventure, Thriller | C38: 4.8 | D38: =_xlfn.RANK.EQ(C38, C38:C1037) -> 317 | E38: 45770 | F38: 2023
A39: The Exorcist: Believer | B39: Horror | C39: 4.8 | D39: =_xlfn.RANK.EQ(C39, C39:C1038) -> 317 | E39: 44700 | F39: 2023
... A196: 321 Action | B196: Drama | C196: 1 | D196: =_xlfn.RANK.EQ(C196, C196:C1195) -> 804 | E196: 10215 | F196: 2020
A197: 2067 | B197: Mystery, Sci-Fi | C197: 4.9 | D197: =_xlfn.RANK.EQ(C197, C197:C1196) -> 215 | E197: 12090 | F197: 2020
A198: Wounds | B198: Drama, Horror, Mystery | C198: 4.1 | D198: =_xlfn.RANK.EQ(C198, C198:C1197) -> 590 | E198: 22267 | F198: 2019
A199: Trauma Center | B199: Action, Thriller | C199: 4 | D199: =_xlfn.RANK.EQ(C199, C199:C1198) -> 607 | E199: 12059 | F199: 2019
A200: The Poison Rose | B200: Crime, Mystery, Thriller | C200: 4.8 | D200: =_xlfn.RANK.EQ(C200, C200:C1199) -> 276 | E200: 11449 | F200: 2019
A201: The Last Boy | B201: Fantasy, Mystery, Sci-Fi | C201: 4.8 | D201: =_xlfn.RANK.EQ(C201, C201:C1200) -> 276 | E201: 10405 | F201: 2019
A202: The Iron Throne | B202: Action, Adventure, Drama | C202: 4 | D202: =_xlfn.RANK.EQ(C202, C202:C1201) -> 605 | E202: 267936 | F202: 2019
A203: The I-Land | B203: Adventure, Drama, Mystery | C203: 4.7 | D203: =_xlfn.RANK.EQ(C203, C203:C1202) -> 354 | E203: 19875 | F203: 2019
A204: The Grudge | B204: Fantasy, Horror | C204: 4.4 | D204: =_xlfn.RANK.EQ(C204, C204:C1203) -> 499 | E204: 30284 | F204: 2019
A205: The Fanatic | B205: Crime, Drama, Horror | C205: 4.1 | D205: =_xlfn.RANK.EQ(C205, C205:C1204) -> 586 | E205: 12749 | F205: 2019
A206: The Courier | B206: Action, Crime, Drama | C206: 4.8 | D206: =_xlfn.RANK.EQ(C206, C206:C1205) -> 276 | E206: 11849 | F206: 2019
A207: Student of the Year 2 | B207: Action, Comedy, Drama | C207: 2.2 | D207: =_xlfn.RANK.EQ(C207, C207:C1206) -> 764 | E207: 22954 | F207: 2019
A208: Secret Obsession | B208: Crime, Drama, Mystery | C208: 4.5 | D208: =_xlfn.RANK.EQ(C208, C208:C1207) -> 460 | E208: 24829 | F208: 2019
A209: Saaho | B209: Action, Thriller | C209: 5.1 | D209: =_xlfn.RANK.EQ(C209, C209:C1208) -> 42 | E209: 24451 | F209: 2019
... A310: Amityville: The Awakening | B310: Horror, Thriller | C310: 4.8 | D310: =_xlfn.RANK.EQ(C310, C310:C1309) -> 244 | E310: 15866 | F310: 2017
A311: Zoolander 2 | B311: Action, Adventure, Comedy | C311: 4.7 | D311: =_xlfn.RANK.EQ(C311, C310:C1310) -> 313 | E311: 77401 | F311: 2016
A312: Yoga Hosers | B312: Action, Comedy, Horror | C312: 4.3 | D312: =_xlfn.RANK.EQ(C312, C312:C1311) -> 472 | E312: 15799 | F312: 2016
A313: The Forest | B313: Horror, Mystery, Thriller | C313: 4.8 | D313: =_xlfn.RANK.EQ(C313, C313:C1312) -> 244 | E313: 46299 | F313: 2016
A314: The Disappointments Room | B314: Drama, Horror, Thriller | C314: 3.9 | D314: =_xlfn.RANK.EQ(C314, C314:C1313) -> 538 | E314: 10882 | F314: 2016
A315: The Darkness | B315: Horror, Thriller | C315: 4.5 | D315: =_xlfn.RANK.EQ(C315, C315:C1314) -> 408 | E315: 17302 | F315: 2016
A316: The Bad Batch | B316: Action, Horror, Mystery | C316: 5.2 | D316: =_xlfn.RANK.EQ(C316, C316:C1315) -> 1 | E316: 36196 | F316: 2016
A317: The 5th Wave | B317: Action, Adventure, Sci-Fi | C317: 5.2 | D317: =_xlfn.RANK.EQ(C317, C317:C1316) -> 1 | E317: 119294 | F317: 2016
A318: Smolensk | B318: Drama, Thriller | C318: 1.2 | D318: =_xlfn.RANK.EQ(C318, C318:C1317) -> 683 | E318: 40233 | F318: 2016
A319: Shut In | B319: Drama, Horror, Mystery | C319: 4.8 | D319: =_xlfn.RANK.EQ(C319, C319:C1318) -> 242 | E319: 15180 | F319: 2016
A320: Precious Cargo | B320: Action, Comedy, Thriller | C320: 4.6 | D320: =_xlfn.RANK.EQ(C320, C320:C1319) -> 357 | E320: 10007 | F320: 2016
A321: Norm of the North | B321: Adventure, Animation, Comedy | C321: 3.4 | D321: =_xlfn.RANK.EQ(C321, C321:C1320) -> 598 | E321: 10288 | F321: 2016
A322: Meet the Blacks | B322: Comedy, Horror | C322: 4.8 | D322: =_xlfn.RANK.EQ(C322, C322:C1321) -> 242 | E322: 38080 | F322: 2016
A323: Max Steel | B323: Action, Adventure, Fantasy | C323: 4.6 | D323: =_xlfn.RANK.EQ(C323, C323:C1322) -> 356 | E323: 20856 | F323: 2016
... A338: AmeriGeddon | B338: Action, Adventure, Drama | C338: 3.8 | D338: =_xlfn.RANK.EQ(C338, C338:C1337) -> 533 | E338: 13397 | F338: 2016
A339: 31 | B339: Horror, Thriller | C339: 5.1 | D339: =_xlfn.RANK.EQ(C339, C339:C1338) -> 32 | E339: 23633 | F339: 2016
A340: Vice | B340: Action, Sci-Fi, Thriller | C340: 4.2 | D340: =_xlfn.RANK.EQ(C340, C340:C1339) -> 473 | E340: 17210 | F340: 2015
A341: The Vatican Tapes | B341: Horror, Thriller | C341: 4.7 | D341: =_xlfn.RANK.EQ(C341, C341:C1340) -> 299 | E341: 19462 | F341: 2015
A342: The Transporter Refueled | B342: Action, Thriller | C342: 5.2 | D342: =_xlfn.RANK.EQ(C342, C342:C1341) -> 1 | E342: 45631 | F342: 2015
A343: The Ridiculous 6 | B343: Action, Adventure, Comedy | C343: 4.9 | D343: =_xlfn.RANK.EQ(C343, C343:C1342) -> 181 | E343: 54734 | F343: 2015
A344: The Lazarus Effect | B344: Horror, Mystery, Sci-Fi | C344: 5.2 | D344: =_xlfn.RANK.EQ(C344, C344:C1343) -> 1 | E344: 46863 | F344: 2015
A345: The Human Centipede III (Final Sequence) | B345: Comedy, Horror | C345: 2.7 | D345: =_xlfn.RANK.EQ(C345, C345:C1344) -> 613 | E345: 20548 | F345: 2015
A346: The Gallows | B346: Horror, Mystery, Thriller | C346: 4.2 | D346: =_xlfn.RANK.EQ(C346, C346:C1345) -> 469 | E346: 21872 | F346: 2015
A347: The D Train | B347: Comedy, Drama | C347: 5.1 | D347: =_xlfn.RANK.EQ(C347, C347:C1346) -> 30 | E347: 11653 | F347: 2015
A348: The Boy Next Door | B348: Thriller | C348: 4.7 | D348: =_xlfn.RANK.EQ(C348, C348:C1347) -> 295 | E348: 46620 | F348: 2015
A349: Superfast! | B349: Action, Comedy, Crime | C349: 4.2 | D349: =_xlfn.RANK.EQ(C349, C349:C1348) -> 467 | E349: 11108 | F349: 2015
A350: Sharknado 3: Oh Hell No! | B350: Action, Adventure, Comedy | C350: 4 | D350: =_xlfn.RANK.EQ(C350, C350:C1349) -> 500 | E350: 14108 | F350: 2015
A351: Return to Sender | B351: Drama, Thriller | C351: 5.1 | D351: =_xlfn.RANK.EQ(C351, C351:C1350) -> 30 | E351: 15018 | F351: 2015
... A506: 67th Street, New York, NY | B506: Crime, Thriller | C506: 2.9 | D506: =_xlfn.RANK.EQ(C506, C506:C1505) -> 455 | E506: 34925 | F506: 2011
A507: 40858 | B507: Horror, Mystery, Thriller | C507: 3.9 | D507: =_xlfn.RANK.EQ(C507, C507:C1506) -> 377 | E507: 12653 | F507: 2011
A508: Yogi Bear | B508: Adventure, Animation, Comedy | C508: 4.6 | D508: =_xlfn.RANK.EQ(C508, C508:C1507) -> 256 | E508: 23739 | F508: 2010
A509: Why Did I Get Married Too? | B509: Comedy, Drama, Romance | C509: 4.7 | D509: =_xlfn.RANK.EQ(C509, C509:C1508) -> 218 | E509: 10423 | F509: 2010
A510: Vanishing on 7th Street | B510: Horror, Mystery, Thriller | C510: 4.9 | D510: =_xlfn.RANK.EQ(C510, C510:C1509) -> 132 | E510: 27687 | F510: 2010
A511: Vampires Suck | B511: Comedy, Horror | C511: 3.4 | D511: =_xlfn.RANK.EQ(C511, C511:C1510) -> 426 | E511: 52393 | F511: 2010
A512: Tooth Fairy | B512: Comedy, Family, Fantasy | C512: 5 | D512: =_xlfn.RANK.EQ(C512, C512:C1511) -> 88 | E512: 50577 | F512: 2010
A513: Titanic II | B513: Action, Adventure, Drama | C513: 1.7 | D513: =_xlfn.RANK.EQ(C513, C513:C1512) -> 481 | E513: 13142 | F513: 2010
A514: The Twilight Saga: Eclipse | B514: Action, Adventure, Drama | C514: 5.1 | D514: =_xlfn.RANK.EQ(C514, C514:C1513) -> 24 | E514: 265386 | F514: 2010
A515: The Romantics | B515: Comedy, Drama, Romance | C515: 5 | D515: =_xlfn.RANK.EQ(C515, C515:C1514) -> 87 | E515: 12596 | F515: 2010
A516: The Last Airbender | B516: Action, Adventure, Family | C516: 4 | D516: =_xlfn.RANK.EQ(C516, C516:C1515) -> 365 | E516: 176827 | F516: 2010
A517: Tekken | B517: Action, Crime, Drama | C517: 4.8 | D517: =_xlfn.RANK.EQ(C517, C517:C1516) -> 166 | E517: 28817 | F517: 2010
A518: Tees Maar Khan | B518: Comedy, Crime | C518: 2.7 | D518: =_xlfn.RANK.EQ(C518, C518:C1517) -> 451 | E518: 14689 | F518: 2010
A519: Smokin' Aces 2: Assassins' Ball | B519: Action, Comedy, Crime | C519: 5 | D519: =_xlfn.RANK.EQ(C519, C519:C1518) -> 87 | E519: 14433 | F519: 2010
... A1001: Plan 9 from Outer Space | B1001: Horror, Sci-Fi | C1001: 3.9 | D1001: =_xlfn.RANK.EQ(C1001, C1001:C2000) -> 1 | E1001: 41105 | F1001: 1957

Sheet Chapter - 3
A1: Release Year | B1: Count OF Titles YearWise | C1: Sum of NumVotes | D1: Avg of AverageRating | E1: Rating Trend
A2: {=_xlfn.UNIQUE('Chapter - 2'!F2:F1001)} -> 2024 | B2: =COUNTIF('Chapter - 1'!F:F, A2) -> 29 | C2: =SUMIF('Chapter - 1'!F:F, A2,'Chapter - 1'!E:E) -> 847025 | D2: =ROUND(AVERAGEIF('Chapter - 1'!F:F, A2,'Chapter - 1'!D:D), 1) -> 4.5
A3: 2023 | B3: =COUNTIF('Chapter - 1'!F:F, A3) -> 33 | C3: =SUMIF('Chapter - 1'!F:F, A3,'Chapter - 1'!E:E) -> 1065820 | D3: =ROUND(AVERAGEIF('Chapter - 1'!F:F, A3,'Chapter - 1'!D:D), 1) -> 4
A4: 2022 | B4: =COUNTIF('Chapter - 1'!F:F, A4) -> 46 | C4: =SUMIF('Chapter - 1'!F:F, A4,'Chapter - 1'!E:E) -> 1581172 | D4: =ROUND(AVERAGEIF('Chapter - 1'!F:F, A4,'Chapter - 1'!D:D), 1) -> 4.2
A5: 2021 | B5: =COUNTIF('Chapter - 1'!F:F, A5) -> 41 | C5: =SUMIF('Chapter - 1'!F:F, A5,'Chapter - 1'!E:E) -> 1314706 | D5: =ROUND(AVERAGEIF('Chapter - 1'!F:F, A5,'Chapter - 1'!D:D), 1) -> 4.1
A6: 2020 | B6: =COUNTIF('Chapter - 1'!F:F, A6) -> 47 | C6: =SUMIF('Chapter - 1'!F:F, A6,'Chapter - 1'!E:E) -> 1145761 | D6: =ROUND(AVERAGEIF('Chapter - 1'!F:F, A6,'Chapter - 1'!D:D), 1) -> 4.1
A7: 2019 | B7: =COUNTIF('Chapter - 1'!F:F, A7) -> 37 | C7: =SUMIF('Chapter - 1'!F:F, A7,'Chapter - 1'!E:E) -> 1045626 | D7: =ROUND(AVERAGEIF('Chapter - 1'!F:F, A7,'Chapter - 1'!D:D), 1) -> 4.2
A8: 2018 | B8: =COUNTIF('Chapter - 1'!F:F, A8) -> 37 | C8: =SUMIF('Chapter - 1'!F:F, A8,'Chapter - 1'!E:E) -> 991257 | D8: =ROUND(AVERAGEIF('Chapter - 1'!F:F, A8,'Chapter - 1'!D:D), 1) -> 4.2
A9: 2017 | B9: =COUNTIF('Chapter - 1'!F:F, A9) -> 39 | C9: =SUMIF('Chapter - 1'!F:F, A9,'Chapter - 1'!E:E) -> 1400603 | D9: =ROUND(AVERAGEIF('Chapter - 1'!F:F, A9,'Chapter - 1'!D:D), 1) -> 4.3
A10: 2016 | B10: =COUNTIF('Chapter - 1'!F:F, A10) -> 29 | C10: =SUMIF('Chapter - 1'!F:F, A10,'Chapter - 1'!E:E) -> 944673 | D10: =ROUND(AVERAGEIF('Chapter - 1'!F:F, A10,'Chapter - 1'!D:D), 1) -> 4.5
A11: 2015 | B11: =COUNTIF('Chapter - 1'!F:F, A11) -> 35 | C11: =SUMIF('Chapter - 1'!F:F, A11,'Chapter - 1'!E:E) -> 1477662 | D11: =ROUND(AVERAGEIF('Chapter - 1'!F:F, A11,'Chapter - 1'!D:D), 1) -> 4.4
A12: 2014 | B12: =COUNTIF('Chapter - 1'!F:F, A12) -> 38 | C12: =SUMIF('Chapter - 1'!F:F, A12,'Chapter - 1'!E:E) -> 1130910 | D12: =ROUND(AVERAGEIF('Chapter - 1'!F:F, A12,'Chapter - 1'!D:D), 1) -> 4.5
A13: 2013 | B13: =COUNTIF('Chapter - 1'!F:F, A13) -> 26 | C13: =SUMIF('Chapter - 1'!F:F, A13,'Chapter - 1'!E:E) -> 1106743 | D13: =ROUND(AVERAGEIF('Chapter - 1'!F:F, A13,'Chapter - 1'!D:D), 1) -> 4.4
A14: 2012 | B14: =COUNTIF('Chapter - 1'!F:F, A14) -> 30 | C14: =SUMIF('Chapter - 1'!F:F, A14,'Chapter - 1'!E:E) -> 886017 | D14: =ROUND(AVERAGEIF('Chapter - 1'!F:F, A14,'Chapter - 1'!D:D), 1) -> 4.5
... A55: 1957 | B55: =COUNTIF('Chapter - 1'!F:F, A55) -> 1 | C55: =SUMIF('Chapter - 1'!F:F, A55,'Chapter - 1'!E:E) -> 41105 | D55: =ROUND(AVERAGEIF('Chapter - 1'!F:F, A55,'Chapter - 1'!D:D), 1) -> 3.9

Sheet Chapter-3 Stocks
A1: Relating Movie Ratings to Stock Performance of Movie Studios
A2: Release Date | B2: Title | C2: Rating | D2: Stock Open | E2: Stock High | F2: Stock Low | G2: Stock Close | H2: Volume
A3: 45467 | B3: The Acolyte | C3: 8.1 | D3: 128.1 | E3: 133.5 | F3: 127.5 | G3: 130 | H3: 10000000
A4: 45468 | B4: The Acolyte | C4: 8.1 | D4: 130 | E4: 134 | F4: 129 | G4: 133 | H4: 12000000
A5: 45469 | B5: The Acolyte | C5: 8.1 | D5: 133 | E5: 136 | F5: 131 | G5: 134.5 | H5: 11000000
A6: 45470 | B6: The Acolyte | C6: 8.1 | D6: 134.5 | E6: 138 | F6: 132.5 | G6: 137 | H6: 9500000
A7: 45471 | B7: The Acolyte | C7: 8.1 | D7: 137 | E7: 140 | F7: 136.5 | G7: 139.5 | H7: 13000000
B9: Stock Price : Open High Low Close Chart | J9: Stock Price: Volume High Low Close Chart | R9: Stock Price : High Low Close Chart

Sheet Chapter - 4
A1: id | B1: title | C1: genres | D1: averageRating | E1: numVotes | F1: releaseYear | G1: AND | H1: OR | I1: NOT | J1: IF
A2: tt13964390 | B2: Under Paris | C2: Action, Drama, Horror | D2: 5.2 | E2: 32479 | F2: 2024 | G2: =IF(AND(D2>5, E2>1000), "Popular", "Not Popular") -> Popular | H2: =IF(OR(ISNUMBER(SEARCH("Action", C2)), ISNUMBER(SEARCH("Drama", C2))), "Action or Drama", IF(OR(ISNUMBER(SEARCH("Horror", C2)), ISNUMBER(SEARCH("Thriller", C2))), "Horror or Thriller", "Other")) -> Action or Drama | I2: =IF(NOT(ISNUMBER(SEARCH("Comedy", C2))), "Not Comedy", "Comedy") -> Not Comedy | J2: =IF(F2>2020, "Recent", "Old") -> Recent | L2: Condition | M2: Comments
A3: tt13186604 | B3: Uglies | C3: Action, Adventure, Drama | D3: 4.7 | E3: 25779 | F3: 2024 | G3: =IF(AND(D3>5, E3>1000), "Popular", "Not Popular") -> Not Popular | H3: =IF(OR(ISNUMBER(SEARCH("Action", C3)), ISNUMBER(SEARCH("Drama", C3))), "Action or Drama", IF(OR(ISNUMBER(SEARCH("Horror", C3)), ISNUMBER(SEARCH("Thriller", C3))), "Horror or Thriller", "Other")) -> Action or Drama | I3: =IF(NOT(ISNUMBER(SEARCH("Comedy", C3))), "Not Comedy", "Comedy") -> Not Comedy | J3: =IF(F3>2020, "Recent", "Old") -> Recent | L3: AND | M3: This formula will label movies as "Popular" if both the average rating is greater than 5 and the number of votes exceeds 1000.
A4: tt5834874 | B4: Trigger Warning | C4: Action, Crime, Thriller | D4: 4.6 | E4: 17570 | F4: 2024 | G4: =IF(AND(D4>5, E4>1000), "Popular", "Not Popular") -> Not Popular | H4: =IF(OR(ISNUMBER(SEARCH("Action", C4)), ISNUMBER(SEARCH("Drama", C4))), "Action or Drama", IF(OR(ISNUMBER(SEARCH("Horror", C4)), ISNUMBER(SEARCH("Thriller", C4))), "Horror or Thriller", "Other")) -> Action or Drama | I4: =IF(NOT(ISNUMBER(SEARCH("Comedy", C4))), "Not Comedy", "Comedy") -> Not Comedy | J4: =IF(F4>2020, "Recent", "Old") -> Recent | L4: OR | M4: Condition based on the genres to check if a movie's genre matches any of the given categories, like "Action," "Drama," "Horror," etc.
A5: tt29114029 | B5: The Tearsmith | C5: Drama, Fantasy, Romance | D5: 5.1 | E5: 10227 | F5: 2024 | G5: =IF(AND(D5>5, E5>1000), "Popular", "Not Popular") -> Popular | H5: =IF(OR(ISNUMBER(SEARCH("Action", C5)), ISNUMBER(SEARCH("Drama", C5))), "Action or Drama", IF(OR(ISNUMBER(SEARCH("Horror", C5)), ISNUMBER(SEARCH("Thriller", C5))), "Horror or Thriller", "Other")) -> Action or Drama | I5: =IF(NOT(ISNUMBER(SEARCH("Comedy", C5))), "Not Comedy", "Comedy") -> Not Comedy | J5: =IF(F5>2020, "Recent", "Old") -> Recent | L5: NOT | M5: Categorize movies as "Not Comedy" if genre does not include "Comedy" and categorize them as "Comedy" if the genre contains "Comedy."
A6: tt22050754 | B6: The Strangers: Chapter 1 | C6: Horror | D6: 4.6 | E6: 19176 | F6: 2024 | G6: =IF(AND(D6>5, E6>1000), "Popular", "Not Popular") -> Not Popular | H6: =IF(OR(ISNUMBER(SEARCH("Action", C6)), ISNUMBER(SEARCH("Drama", C6))), "Action or Drama", IF(OR(ISNUMBER(SEARCH("Horror", C6)), ISNUMBER(SEARCH("Thriller", C6))), "Horror or Thriller", "Other")) -> Horror or Thriller | I6: =IF(NOT(ISNUMBER(SEARCH("Comedy", C6))), "Not Comedy", "Comedy") -> Not Comedy | J6: =IF(F6>2020, "Recent", "Old") -> Recent | L6: IF | M6: This will label movies as "Recent" if the release year is after 2020, otherwise as "Old".
A7: tt27729779 | B7: The Platform 2 | C7: Horror, Sci-Fi, Thriller | D7: 5 | E7: 29234 | F7: 2024 | G7: =IF(AND(D7>5, E7>1000), "Popular", "Not Popular") -> Not Popular | H7: =IF(OR(ISNUMBER(SEARCH("Action", C7)), ISNUMBER(SEARCH("Drama", C7))), "Action or Drama", IF(OR(ISNUMBER(SEARCH("Horror", C7)), ISNUMBER(SEARCH("Thriller", C7))), "Horror or Thriller", "Other")) -> Horror or Thriller | I7: =IF(NOT(ISNUMBER(SEARCH("Comedy", C7))), "Not Comedy", "Comedy") -> Not Comedy | J7: =IF(F7>2020, "Recent", "Old") -> Recent
A8: tt4196566 | B8: The Deliverance | C8: Horror, Thriller | D8: 5.1 | E8: 19367 | F8: 2024 | G8: =IF(AND(D8>5, E8>1000), "Popular", "Not Popular") -> Popular | H8: =IF(OR(ISNUMBER(SEARCH("Action", C8)), ISNUMBER(SEARCH("Drama", C8))), "Action or Drama", IF(OR(ISNUMBER(SEARCH("Horror", C8)), ISNUMBER(SEARCH("Thriller", C8))), "Horror or Thriller", "Other")) -> Horror or Thriller | I8: =IF(NOT(ISNUMBER(SEARCH("Comedy", C8))), "Not Comedy", "Comedy") -> Not Comedy | J8: =IF(F8>2020, "Recent", "Old") -> Recent
A9: tt1340094 | B9: The Crow | C9: Action, Crime, Fantasy | D9: 4.7 | E9: 24427 | F9: 2024 | G9: =IF(AND(D9>5, E9>1000), "Popular", "Not Popular") -> Not Popular | H9: =IF(OR(ISNUMBER(SEARCH("Action", C9)), ISNUMBER(SEARCH("Drama", C9))), "Action or Drama", IF(OR(ISNUMBER(SEARCH("Horror", C9)), ISNUMBER(SEARCH("Thriller", C9))), "Horror or Thriller", "Other")) -> Action or Drama | I9: =IF(NOT(ISNUMBER(SEARCH("Comedy", C9))), "Not Comedy", "Comedy") -> Not Comedy | J9: =IF(F9>2020, "Recent", "Old") -> Recent
A10: tt30007864 | B10: The American Society of Magical Negroes | C10: Comedy, Fantasy | D10: 3.6 | E10: 10937 | F10: 2024 | G10: =IF(AND(D10>5, E10>1000), "Popular", "Not Popular") -> Not Popular | H10: =IF(OR(ISNUMBER(SEARCH("Action", C10)), ISNUMBER(SEARCH("Drama", C10))), "Action or Drama", IF(OR(ISNUMBER(SEARCH("Horror", C10)), ISNUMBER(SEARCH("Thriller", C10))), "Horror or Thriller", "Other")) -> Other | I10: =IF(NOT(ISNUMBER(SEARCH("Comedy", C10))), "Not Comedy", "Comedy") -> Comedy | J10: =IF(F10>2020, "Recent", "Old") -> Recent
A11: tt12262202 | B11: The Acolyte | C11: Action, Adventure, Drama | D11: 4.1 | E11: 124735 | F11: 2024 | G11: =IF(AND(D11>5, E11>1000), "Popular", "Not Popular") -> Not Popular | H11: =IF(OR(ISNUMBER(SEARCH("Action", C11)), ISNUMBER(SEARCH("Drama", C11))), "Action or Drama", IF(OR(ISNUMBER(SEARCH("Horror", C11)), ISNUMBER(SEARCH("Thriller", C11))), "Horror or Thriller", "Other")) -> Action or Drama | I11: =IF(NOT(ISNUMBER(SEARCH("Comedy", C11))), "Not Comedy", "Comedy") -> Not Comedy | J11: =IF(F11>2020, "Recent", "Old") -> Recent
A12: tt15387054 | B12: Teach/Corrupt | C12: Action, Adventure, Drama | D12: 5.1 | E12: 12964 | F12: 2024 | G12: =IF(AND(D12>5, E12>1000), "Popular", "Not Popular") -> Popular | H12: =IF(OR(ISNUMBER(SEARCH("Action", C12)), ISNUMBER(SEARCH("Drama", C12))), "Action or Drama", IF(OR(ISNUMBER(SEARCH("Horror", C12)), ISNUMBER(SEARCH("Thriller", C12))), "Horror or Thriller", "Other")) -> Action or Drama | I12: =IF(NOT(ISNUMBER(SEARCH("Comedy", C12))), "Not Comedy", "Comedy") -> Not Comedy | J12: =IF(F12>2020, "Recent", "Old") -> Recent
A13: tt14088510 | B13: Tarot | C13: Horror | D13: 4.8 | E13: 25522 | F13: 2024 | G13: =IF(AND(D13>5, E13>1000), "Popular", "Not Popular") -> Not Popular | H13: =IF(OR(ISNUMBER(SEARCH("Action", C13)), ISNUMBER(SEARCH("Drama", C13))), "Action or Drama", IF(OR(ISNUMBER(SEARCH("Horror", C13)), ISNUMBER(SEARCH("Thriller", C13))), "Horror or Thriller", "Other")) -> Horror or Thriller | I13: =IF(NOT(ISNUMBER(SEARCH("Comedy", C13))), "Not Comedy", "Comedy") -> Not Comedy | J13: =IF(F13>2020, "Recent", "Old") -> Recent
A14: tt15387022 | B14: Revenge/Justice | C14: Action, Adventure, Drama | D14: 5.1 | E14: 23343 | F14: 2024 | G14: =IF(AND(D14>5, E14>1000), "Popular", "Not Popular") -> Popular | H14: =IF(OR(ISNUMBER(SEARCH("Action", C14)), ISNUMBER(SEARCH("Drama", C14))), "Action or Drama", IF(OR(ISNUMBER(SEARCH("Horror", C14)), ISNUMBER(SEARCH("Thriller", C14))), "Horror or Thriller", "Other")) -> Action or Drama | I14: =IF(NOT(ISNUMBER(SEARCH("Comedy", C14))), "Not Comedy", "Comedy") -> Not Comedy | J14: =IF(F14>2020, "Recent", "Old") -> Recent
A15: tt19857862 | B15: Now or Never! | C15: Adventure, Biography, Drama | D15: 2 | E15: 16400 | F15: 2024 | G15: =IF(AND(D15>5, E15>1000), "Popular", "Not Popular") -> Not Popular | H15: =IF(OR(ISNUMBER(SEARCH("Action", C15)), ISNUMBER(SEARCH("Drama", C15))), "Action or Drama", IF(OR(ISNUMBER(SEARCH("Horror", C15)), ISNUMBER(SEARCH("Thriller", C15))), "Horror or Thriller", "Other")) -> Action or Drama | I15: =IF(NOT(ISNUMBER(SEARCH("Comedy", C15))), "Not Comedy", "Comedy") -> Not Comedy | J15: =IF(F15>2020, "Recent", "Old") -> Recent
A16: tt9682428 | B16: Night Swim | C16: Horror, Thriller | D16: 4.7 | E16: 25006 | F16: 2024 | G16: =IF(AND(D16>5, E16>1000), "Popular", "Not Popular") -> Not Popular | H16: =IF(OR(ISNUMBER(SEARCH("Action", C16)), ISNUMBER(SEARCH("Drama", C16))), "Action or Drama", IF(OR(ISNUMBER(SEARCH("Horror", C16)), ISNUMBER(SEARCH("Thriller", C16))), "Horror or Thriller", "Other")) -> Horror or Thriller | I16: =IF(NOT(ISNUMBER(SEARCH("Comedy", C16))), "Not Comedy", "Comedy") -> Not Comedy | J16: =IF(F16>2020, "Recent", "Old") -> Recent
A17: tt26926267 | B17: Mother of the Bride | C17: Comedy, Drama, Romance | D17: 4.8 | E17: 15187 | F17: 2024 | G17: =IF(AND(D17>5, E17>1000), "Popular", "Not Popular") -> Not Popular | H17: =IF(OR(ISNUMBER(SEARCH("Action", C17)), ISNUMBER(SEARCH("Drama", C17))), "Action or Drama", IF(OR(ISNUMBER(SEARCH("Horror", C17)), ISNUMBER(SEARCH("Thriller", C17))), "Horror or Thriller", "Other")) -> Action or Drama | I17: =IF(NOT(ISNUMBER(SEARCH("Comedy", C17))), "Not Comedy", "Comedy") -> Comedy | J17: =IF(F17>2020, "Recent", "Old") -> Recent
A18: tt10128846 | B18: Megalopolis | C18: Drama, Fantasy, Sci-Fi | D18: 5.1 | E18: 17457 | F18: 2024 | G18: =IF(AND(D18>5, E18>1000), "Popular", "Not Popular") -> Popular | H18: =IF(OR(ISNUMBER(SEARCH("Action", C18)), ISNUMBER(SEARCH("Drama", C18))), "Action or Drama", IF(OR(ISNUMBER(SEARCH("Horror", C18)), ISNUMBER(SEARCH("Thriller", C18))), "Horror or Thriller", "Other")) -> Action or Drama | I18: =IF(NOT(ISNUMBER(SEARCH("Comedy", C18))), "Not Comedy", "Comedy") -> Not Comedy | J18: =IF(F18>2020, "Recent", "Old") -> Recent
... A196: tt13423846 | B196: 321 Action | C196: Drama | D196: 1 | E196: 10215 | F196: 2020 | G196: =IF(AND(D196>5, E196>1000), "Popular", "Not Popular") -> Not Popular | H196: =IF(OR(ISNUMBER(SEARCH("Action", C196)), ISNUMBER(SEARCH("Drama", C196))), "Action or Drama", IF(OR(ISNUMBER(SEARCH("Horror", C196)), ISNUMBER(SEARCH("Thriller", C196))), "Horror or Thriller", "Other")) -> Action or Drama | I196: =IF(NOT(ISNUMBER(SEARCH("Comedy", C196))), "Not Comedy", "Comedy") -> Not Comedy | J196: =IF(F196>2020, "Recent", "Old") -> Old
A197: tt1918734 | B197: 2067 | C197: Mystery, Sci-Fi | D197: 4.9 | E197: 12090 | F197: 2020 | G197: =IF(AND(D197>5, E197>1000), "Popular", "Not Popular") -> Not Popular | H197: =IF(OR(ISNUMBER(SEARCH("Action", C197)), ISNUMBER(SEARCH("Drama", C197))), "Action or Drama", IF(OR(ISNUMBER(SEARCH("Horror", C197)), ISNUMBER(SEARCH("Thriller", C197))), "Horror or Thriller", "Other")) -> Other | I197: =IF(NOT(ISNUMBER(SEARCH("Comedy", C197))), "Not Comedy", "Comedy") -> Not Comedy | J197: =IF(F197>2020, "Recent", "Old") -> Old
A198: tt5913798 | B198: Wounds | C198: Drama, Horror, Mystery | D198: 4.1 | E198: 22267 | F198: 2019 | G198: =IF(AND(D198>5, E198>1000), "Popular", "Not Popular") -> Not Popular | H198: =IF(OR(ISNUMBER(SEARCH("Action", C198)), ISNUMBER(SEARCH("Drama", C198))), "Action or Drama", IF(OR(ISNUMBER(SEARCH("Horror", C198)), ISNUMBER(SEARCH("Thriller", C198))), "Horror or Thriller", "Other")) -> Action or Drama | I198: =IF(NOT(ISNUMBER(SEARCH("Comedy", C198))), "Not Comedy", "Comedy") -> Not Comedy | J198: =IF(F198>2020, "Recent", "Old") -> Old
A199: tt9625664 | B199: Trauma Center | C199: Action, Thriller | D199: 4 | E199: 12059 | F199: 2019 | G199: =IF(AND(D199>5, E199>1000), "Popular", "Not Popular") -> Not Popular | H199: =IF(OR(ISNUMBER(SEARCH("Action", C199)), ISNUMBER(SEARCH("Drama", C199))), "Action or Drama", IF(OR(ISNUMBER(SEARCH("Horror", C199)), ISNUMBER(SEARCH("Thriller", C199))), "Horror or Thriller", "Other")) -> Action or Drama | I199: =IF(NOT(ISNUMBER(SEARCH("Comedy", C199))), "Not Comedy", "Comedy") -> Not Comedy | J199: =IF(F199>2020, "Recent", "Old") -> Old
A200: tt5862166 | B200: The Poison Rose | C200: Crime, Mystery, Thriller | D200: 4.8 | E200: 11449 | F200: 2019 | G200: =IF(AND(D200>5, E200>1000), "Popular", "Not Popular") -> Not Popular | H200: =IF(OR(ISNUMBER(SEARCH("Action", C200)), ISNUMBER(SEARCH("Drama", C200))), "Action or Drama", IF(OR(ISNUMBER(SEARCH("Horror", C200)), ISNUMBER(SEARCH("Thriller", C200))), "Horror or Thriller", "Other")) -> Horror or Thriller | I200: =IF(NOT(ISNUMBER(SEARCH("Comedy", C200))), "Not Comedy", "Comedy") -> Not Comedy | J200: =IF(F200>2020, "Recent", "Old") -> Old
A201: tt4157728 | B201: The Last Boy | C201: Fantasy, Mystery, Sci-Fi | D201: 4.8 | E201: 10405 | F201: 2019 | G201: =IF(AND(D201>5, E201>1000), "Popular", "Not Popular") -> Not Popular | H201: =IF(OR(ISNUMBER(SEARCH("Action", C201)), ISNUMBER(SEARCH("Drama", C201))), "Action or Drama", IF(OR(ISNUMBER(SEARCH("Horror", C201)), ISNUMBER(SEARCH("Thriller", C201))), "Horror or Thriller", "Other")) -> Other | I201: =IF(NOT(ISNUMBER(SEARCH("Comedy", C201))), "Not Comedy", "Comedy") -> Not Comedy | J201: =IF(F201>2020, "Recent", "Old") -> Old
A202: tt6027920 | B202: The Iron Throne | C202: Action, Adventure, Drama | D202: 4 | E202: 267936 | F202: 2019 | G202: =IF(AND(D202>5, E202>1000), "Popular", "Not Popular") -> Not Popular | H202: =IF(OR(ISNUMBER(SEARCH("Action", C202)), ISNUMBER(SEARCH("Drama", C202))), "Action or Drama", IF(OR(ISNUMBER(SEARCH("Horror", C202)), ISNUMBER(SEARCH("Thriller", C202))), "Horror or Thriller", "Other")) -> Action or Drama | I202: =IF(NOT(ISNUMBER(SEARCH("Comedy", C202))), "Not Comedy", "Comedy") -> Not Comedy | J202: =IF(F202>2020, "Recent", "Old") -> Old
A203: tt9067020 | B203: The I-Land | C203: Adventure, Drama, Mystery | D203: 4.7 | E203: 19875 | F203: 2019 | G203: =IF(AND(D203>5, E203>1000), "Popular", "Not Popular") -> Not Popular | H203: =IF(OR(ISNUMBER(SEARCH("Action", C203)), ISNUMBER(SEARCH("Drama", C203))), "Action or Drama", IF(OR(ISNUMBER(SEARCH("Horror", C203)), ISNUMBER(SEARCH("Thriller", C203))), "Horror or Thriller", "Other")) -> Action or Drama | I203: =IF(NOT(ISNUMBER(SEARCH("Comedy", C203))), "Not Comedy", "Comedy") -> Not Comedy | J203: =IF(F203>2020, "Recent", "Old") -> Old
A204: tt3612126 | B204: The Grudge | C204: Fantasy, Horror | D204: 4.4 | E204: 30284 | F204: 2019 | G204: =IF(AND(D204>5, E204>1000), "Popular", "Not Popular") -> Not Popular | H204: =IF(OR(ISNUMBER(SEARCH("Action", C204)), ISNUMBER(SEARCH("Drama", C204))), "Action or Drama", IF(OR(ISNUMBER(SEARCH("Horror", C204)), ISNUMBER(SEARCH("Thriller", C204))), "Horror or Thriller", "Other")) -> Horror or Thriller | I204: =IF(NOT(ISNUMBER(SEARCH("Comedy", C204))), "Not Comedy", "Comedy") -> Not Comedy | J204: =IF(F204>2020, "Recent", "Old") -> Old
A205: tt7869070 | B205: The Fanatic | C205: Crime, Drama, Horror | D205: 4.1 | E205: 12749 | F205: 2019 | G205: =IF(AND(D205>5, E205>1000), "Popular", "Not Popular") -> Not Popular | H205: =IF(OR(ISNUMBER(SEARCH("Action", C205)), ISNUMBER(SEARCH("Drama", C205))), "Action or Drama", IF(OR(ISNUMBER(SEARCH("Horror", C205)), ISNUMBER(SEARCH("Thriller", C205))), "Horror or Thriller", "Other")) -> Action or Drama | I205: =IF(NOT(ISNUMBER(SEARCH("Comedy", C205))), "Not Comedy", "Comedy") -> Not Comedy | J205: =IF(F205>2020, "Recent", "Old") -> Old
A206: tt8075016 | B206: The Courier | C206: Action, Crime, Drama | D206: 4.8 | E206: 11849 | F206: 2019 | G206: =IF(AND(D206>5, E206>1000), "Popular", "Not Popular") -> Not Popular | H206: =IF(OR(ISNUMBER(SEARCH("Action", C206)), ISNUMBER(SEARCH("Drama", C206))), "Action or Drama", IF(OR(ISNUMBER(SEARCH("Horror", C206)), ISNUMBER(SEARCH("Thriller", C206))), "Horror or Thriller", "Other")) -> Action or Drama | I206: =IF(NOT(ISNUMBER(SEARCH("Comedy", C206))), "Not Comedy", "Comedy") -> Not Comedy | J206: =IF(F206>2020, "Recent", "Old") -> Old
A207: tt7255568 | B207: Student of the Year 2 | C207: Action, Comedy, Drama | D207: 2.2 | E207: 22954 | F207: 2019 | G207: =IF(AND(D207>5, E207>1000), "Popular", "Not Popular") -> Not Popular | H207: =IF(OR(ISNUMBER(SEARCH("Action", C207)), ISNUMBER(SEARCH("Drama", C207))), "Action or Drama", IF(OR(ISNUMBER(SEARCH("Horror", C207)), ISNUMBER(SEARCH("Thriller", C207))), "Horror or Thriller", "Other")) -> Action or Drama | I207: =IF(NOT(ISNUMBER(SEARCH("Comedy", C207))), "Not Comedy", "Comedy") -> Comedy | J207: =IF(F207>2020, "Recent", "Old") -> Old
A208: tt9419834 | B208: Secret Obsession | C208: Crime, Drama, Mystery | D208: 4.5 | E208: 24829 | F208: 2019 | G208: =IF(AND(D208>5, E208>1000), "Popular", "Not Popular") -> Not Popular | H208: =IF(OR(ISNUMBER(SEARCH("Action", C208)), ISNUMBER(SEARCH("Drama", C208))), "Action or Drama", IF(OR(ISNUMBER(SEARCH("Horror", C208)), ISNUMBER(SEARCH("Thriller", C208))), "Horror or Thriller", "Other")) -> Action or Drama | I208: =IF(NOT(ISNUMBER(SEARCH("Comedy", C208))), "Not Comedy", "Comedy") -> Not Comedy | J208: =IF(F208>2020, "Recent", "Old") -> Old
A209: tt6836936 | B209: Saaho | C209: Action, Thriller | D209: 5.1 | E209: 24451 | F209: 2019 | G209: =IF(AND(D209>5, E209>1000), "Popular", "Not Popular") -> Popular | H209: =IF(OR(ISNUMBER(SEARCH("Action", C209)), ISNUMBER(SEARCH("Drama", C209))), "Action or Drama", IF(OR(ISNUMBER(SEARCH("Horror", C209)), ISNUMBER(SEARCH("Thriller", C209))), "Horror or Thriller", "Other")) -> Action or Drama | I209: =IF(NOT(ISNUMBER(SEARCH("Comedy", C209))), "Not Comedy", "Comedy") -> Not Comedy | J209: =IF(F209>2020, "Recent", "Old") -> Old
... A338: tt4059702 | B338: AmeriGeddon | C338: Action, Adventure, Drama | D338: 3.8 | E338: 13397 | F338: 2016 | G338: =IF(AND(D338>5, E338>1000), "Popular", "Not Popular") -> Not Popular | H338: =IF(OR(ISNUMBER(SEARCH("Action", C338)), ISNUMBER(SEARCH("Drama", C338))), "Action or Drama", IF(OR(ISNUMBER(SEARCH("Horror", C338)), ISNUMBER(SEARCH("Thriller", C338))), "Horror or Thriller", "Other")) -> Action or Drama | I338: =IF(NOT(ISNUMBER(SEARCH("Comedy", C338))), "Not Comedy", "Comedy") -> Not Comedy | J338: =IF(F338>2020, "Recent", "Old") -> Old
A339: tt3835080 | B339: 31 | C339: Horror, Thriller | D339: 5.1 | E339: 23633 | F339: 2016 | G339: =IF(AND(D339>5, E339>1000), "Popular", "Not Popular") -> Popular | H339: =IF(OR(ISNUMBER(SEARCH("Action", C339)), ISNUMBER(SEARCH("Drama", C339))), "Action or Drama", IF(OR(ISNUMBER(SEARCH("Horror", C339)), ISNUMBER(SEARCH("Thriller", C339))), "Horror or Thriller", "Other")) -> Horror or Thriller | I339: =IF(NOT(ISNUMBER(SEARCH("Comedy", C339))), "Not Comedy", "Comedy") -> Not Comedy | J339: =IF(F339>2020, "Recent", "Old") -> Old
A340: tt3480796 | B340: Vice | C340: Action, Sci-Fi, Thriller | D340: 4.2 | E340: 17210 | F340: 2015 | G340: =IF(AND(D340>5, E340>1000), "Popular", "Not Popular") -> Not Popular | H340: =IF(OR(ISNUMBER(SEARCH("Action", C340)), ISNUMBER(SEARCH("Drama", C340))), "Action or Drama", IF(OR(ISNUMBER(SEARCH("Horror", C340)), ISNUMBER(SEARCH("Thriller", C340))), "Horror or Thriller", "Other")) -> Action or Drama | I340: =IF(NOT(ISNUMBER(SEARCH("Comedy", C340))), "Not Comedy", "Comedy") -> Not Comedy | J340: =IF(F340>2020, "Recent", "Old") -> Old
A341: tt1524575 | B341: The Vatican Tapes | C341: Horror, Thriller | D341: 4.7 | E341: 19462 | F341: 2015 | G341: =IF(AND(D341>5, E341>1000), "Popular", "Not Popular") -> Not Popular | H341: =IF(OR(ISNUMBER(SEARCH("Action", C341)), ISNUMBER(SEARCH("Drama", C341))), "Action or Drama", IF(OR(ISNUMBER(SEARCH("Horror", C341)), ISNUMBER(SEARCH("Thriller", C341))), "Horror or Thriller", "Other")) -> Horror or Thriller | I341: =IF(NOT(ISNUMBER(SEARCH("Comedy", C341))), "Not Comedy", "Comedy") -> Not Comedy | J341: =IF(F341>2020, "Recent", "Old") -> Old
A342: tt2938956 | B342: The Transporter Refueled | C342: Action, Thriller | D342: 5.2 | E342: 45631 | F342: 2015 | G342: =IF(AND(D342>5, E342>1000), "Popular", "Not Popular") -> Popular | H342: =IF(OR(ISNUMBER(SEARCH("Action", C342)), ISNUMBER(SEARCH("Drama", C342))), "Action or Drama", IF(OR(ISNUMBER(SEARCH("Horror", C342)), ISNUMBER(SEARCH("Thriller", C342))), "Horror or Thriller", "Other")) -> Action or Drama | I342: =IF(NOT(ISNUMBER(SEARCH("Comedy", C342))), "Not Comedy", "Comedy") -> Not Comedy | J342: =IF(F342>2020, "Recent", "Old") -> Old
A343: tt2479478 | B343: The Ridiculous 6 | C343: Action, Adventure, Comedy | D343: 4.9 | E343: 54734 | F343: 2015 | G343: =IF(AND(D343>5, E343>1000), "Popular", "Not Popular") -> Not Popular | H343: =IF(OR(ISNUMBER(SEARCH("Action", C343)), ISNUMBER(SEARCH("Drama", C343))), "Action or Drama", IF(OR(ISNUMBER(SEARCH("Horror", C343)), ISNUMBER(SEARCH("Thriller", C343))), "Horror or Thriller", "Other")) -> Action or Drama | I343: =IF(NOT(ISNUMBER(SEARCH("Comedy", C343))), "Not Comedy", "Comedy") -> Comedy | J343: =IF(F343>2020, "Recent", "Old") -> Old
A344: tt2918436 | B344: The Lazarus Effect | C344: Horror, Mystery, Sci-Fi | D344: 5.2 | E344: 46863 | F344: 2015 | G344: =IF(AND(D344>5, E344>1000), "Popular", "Not Popular") -> Popular | H344: =IF(OR(ISNUMBER(SEARCH("Action", C344)), ISNUMBER(SEARCH("Drama", C344))), "Action or Drama", IF(OR(ISNUMBER(SEARCH("Horror", C344)), ISNUMBER(SEARCH("Thriller", C344))), "Horror or Thriller", "Other")) -> Horror or Thriller | I344: =IF(NOT(ISNUMBER(SEARCH("Comedy", C344))), "Not Comedy", "Comedy") -> Not Comedy | J344: =IF(F344>2020, "Recent", "Old") -> Old
A345: tt1883367 | B345: The Human Centipede III (Final Sequence) | C345: Comedy, Horror | D345: 2.7 | E345: 20548 | F345: 2015 | G345: =IF(AND(D345>5, E345>1000), "Popular", "Not Popular") -> Not Popular | H345: =IF(OR(ISNUMBER(SEARCH("Action", C345)), ISNUMBER(SEARCH("Drama", C345))), "Action or Drama", IF(OR(ISNUMBER(SEARCH("Horror", C345)), ISNUMBER(SEARCH("Thriller", C345))), "Horror or Thriller", "Other")) -> Horror or Thriller | I345: =IF(NOT(ISNUMBER(SEARCH("Comedy", C345))), "Not Comedy", "Comedy") -> Comedy | J345: =IF(F345>2020, "Recent", "Old") -> Old
A346: tt2309260 | B346: The Gallows | C346: Horror, Mystery, Thriller | D346: 4.2 | E346: 21872 | F346: 2015 | G346: =IF(AND(D346>5, E346>1000), "Popular", "Not Popular") -> Not Popular | H346: =IF(OR(ISNUMBER(SEARCH("Action", C346)), ISNUMBER(SEARCH("Drama", C346))), "Action or Drama", IF(OR(ISNUMBER(SEARCH("Horror", C346)), ISNUMBER(SEARCH("Thriller", C346))), "Horror or Thriller", "Other")) -> Horror or Thriller | I346: =IF(NOT(ISNUMBER(SEARCH("Comedy", C346))), "Not Comedy", "Comedy") -> Not Comedy | J346: =IF(F346>2020, "Recent", "Old") -> Old
A347: tt2690138 | B347: The D Train | C347: Comedy, Drama | D347: 5.1 | E347: 11653 | F347: 2015 | G347: =IF(AND(D347>5, E347>1000), "Popular", "Not Popular") -> Popular | H347: =IF(OR(ISNUMBER(SEARCH("Action", C347)), ISNUMBER(SEARCH("Drama", C347))), "Action or Drama", IF(OR(ISNUMBER(SEARCH("Horror", C347)), ISNUMBER(SEARCH("Thriller", C347))), "Horror or Thriller", "Other")) -> Action or Drama | I347: =IF(NOT(ISNUMBER(SEARCH("Comedy", C347))), "Not Comedy", "Comedy") -> Comedy | J347: =IF(F347>2020, "Recent", "Old") -> Old
A348: tt3181822 | B348: The Boy Next Door | C348: Thriller | D348: 4.7 | E348: 46620 | F348: 2015 | G348: =IF(AND(D348>5, E348>1000), "Popular", "Not Popular") -> Not Popular | H348: =IF(OR(ISNUMBER(SEARCH("Action", C348)), ISNUMBER(SEARCH("Drama", C348))), "Action or Drama", IF(OR(ISNUMBER(SEARCH("Horror", C348)), ISNUMBER(SEARCH("Thriller", C348))), "Horror or Thriller", "Other")) -> Horror or Thriller | I348: =IF(NOT(ISNUMBER(SEARCH("Comedy", C348))), "Not Comedy", "Comedy") -> Not Comedy | J348: =IF(F348>2020, "Recent", "Old") -> Old
A349: tt2933474 | B349: Superfast! | C349: Action, Comedy, Crime | D349: 4.2 | E349: 11108 | F349: 2015 | G349: =IF(AND(D349>5, E349>1000), "Popular", "Not Popular") -> Not Popular | H349: =IF(OR(ISNUMBER(SEARCH("Action", C349)), ISNUMBER(SEARCH("Drama", C349))), "Action or Drama", IF(OR(ISNUMBER(SEARCH("Horror", C349)), ISNUMBER(SEARCH("Thriller", C349))), "Horror or Thriller", "Other")) -> Action or Drama | I349: =IF(NOT(ISNUMBER(SEARCH("Comedy", C349))), "Not Comedy", "Comedy") -> Comedy | J349: =IF(F349>2020, "Recent", "Old") -> Old
A350: tt3899796 | B350: Sharknado 3: Oh Hell No! | C350: Action, Adventure, Comedy | D350: 4 | E350: 14108 | F350: 2015 | G350: =IF(AND(D350>5, E350>1000), "Popular", "Not Popular") -> Not Popular | H350: =IF(OR(ISNUMBER(SEARCH("Action", C350)), ISNUMBER(SEARCH("Drama", C350))), "Action or Drama", IF(OR(ISNUMBER(SEARCH("Horror", C350)), ISNUMBER(SEARCH("Thriller", C350))), "Horror or Thriller", "Other")) -> Action or Drama | I350: =IF(NOT(ISNUMBER(SEARCH("Comedy", C350))), "Not Comedy", "Comedy") -> Comedy | J350: =IF(F350>2020, "Recent", "Old") -> Old
A351: tt2948790 | B351: Return to Sender | C351: Drama, Thriller | D351: 5.1 | E351: 15018 | F351: 2015 | G351: =IF(AND(D351>5, E351>1000), "Popular", "Not Popular") -> Popular | H351: =IF(OR(ISNUMBER(SEARCH("Action", C351)), ISNUMBER(SEARCH("Drama", C351))), "Action or Drama", IF(OR(ISNUMBER(SEARCH("Horror", C351)), ISNUMBER(SEARCH("Thriller", C351))), "Horror or Thriller", "Other")) -> Action or Drama | I351: =IF(NOT(ISNUMBER(SEARCH("Comedy", C351))), "Not Comedy", "Comedy") -> Not Comedy | J351: =IF(F351>2020, "Recent", "Old") -> Old
... A506: tt1788979 | B506: 67th Street, New York, NY | C506: Crime, Thriller | D506: 2.9 | E506: 34925 | F506: 2011 | G506: =IF(AND(D506>5, E506>1000), "Popular", "Not Popular") -> Not Popular | H506: =IF(OR(ISNUMBER(SEARCH("Action", C506)), ISNUMBER(SEARCH("Drama", C506))), "Action or Drama", IF(OR(ISNUMBER(SEARCH("Horror", C506)), ISNUMBER(SEARCH("Thriller", C506))), "Horror or Thriller", "Other")) -> Horror or Thriller | I506: =IF(NOT(ISNUMBER(SEARCH("Comedy", C506))), "Not Comedy", "Comedy") -> Not Comedy | J506: =IF(F506>2020, "Recent", "Old") -> Old
A507: tt1712159 | B507: 40858 | C507: Horror, Mystery, Thriller | D507: 3.9 | E507: 12653 | F507: 2011 | G507: =IF(AND(D507>5, E507>1000), "Popular", "Not Popular") -> Not Popular | H507: =IF(OR(ISNUMBER(SEARCH("Action", C507)), ISNUMBER(SEARCH("Drama", C507))), "Action or Drama", IF(OR(ISNUMBER(SEARCH("Horror", C507)), ISNUMBER(SEARCH("Thriller", C507))), "Horror or Thriller", "Other")) -> Horror or Thriller | I507: =IF(NOT(ISNUMBER(SEARCH("Comedy", C507))), "Not Comedy", "Comedy") -> Not Comedy | J507: =IF(F507>2020, "Recent", "Old") -> Old
A508: tt1302067 | B508: Yogi Bear | C508: Adventure, Animation, Comedy | D508: 4.6 | E508: 23739 | F508: 2010 | G508: =IF(AND(D508>5, E508>1000), "Popular", "Not Popular") -> Not Popular | H508: =IF(OR(ISNUMBER(SEARCH("Action", C508)), ISNUMBER(SEARCH("Drama", C508))), "Action or Drama", IF(OR(ISNUMBER(SEARCH("Horror", C508)), ISNUMBER(SEARCH("Thriller", C508))), "Horror or Thriller", "Other")) -> Other | I508: =IF(NOT(ISNUMBER(SEARCH("Comedy", C508))), "Not Comedy", "Comedy") -> Comedy | J508: =IF(F508>2020, "Recent", "Old") -> Old
A509: tt1391137 | B509: Why Did I Get Married Too? | C509: Comedy, Drama, Romance | D509: 4.7 | E509: 10423 | F509: 2010 | G509: =IF(AND(D509>5, E509>1000), "Popular", "Not Popular") -> Not Popular | H509: =IF(OR(ISNUMBER(SEARCH("Action", C509)), ISNUMBER(SEARCH("Drama", C509))), "Action or Drama", IF(OR(ISNUMBER(SEARCH("Horror", C509)), ISNUMBER(SEARCH("Thriller", C509))), "Horror or Thriller", "Other")) -> Action or Drama | I509: =IF(NOT(ISNUMBER(SEARCH("Comedy", C509))), "Not Comedy", "Comedy") -> Comedy | J509: =IF(F509>2020, "Recent", "Old") -> Old
A510: tt1452628 | B510: Vanishing on 7th Street | C510: Horror, Mystery, Thriller | D510: 4.9 | E510: 27687 | F510: 2010 | G510: =IF(AND(D510>5, E510>1000), "Popular", "Not Popular") -> Not Popular | H510: =IF(OR(ISNUMBER(SEARCH("Action", C510)), ISNUMBER(SEARCH("Drama", C510))), "Action or Drama", IF(OR(ISNUMBER(SEARCH("Horror", C510)), ISNUMBER(SEARCH("Thriller", C510))), "Horror or Thriller", "Other")) -> Horror or Thriller | I510: =IF(NOT(ISNUMBER(SEARCH("Comedy", C510))), "Not Comedy", "Comedy") -> Not Comedy | J510: =IF(F510>2020, "Recent", "Old") -> Old
A511: tt1666186 | B511: Vampires Suck | C511: Comedy, Horror | D511: 3.4 | E511: 52393 | F511: 2010 | G511: =IF(AND(D511>5, E511>1000), "Popular", "Not Popular") -> Not Popular | H511: =IF(OR(ISNUMBER(SEARCH("Action", C511)), ISNUMBER(SEARCH("Drama", C511))), "Action or Drama", IF(OR(ISNUMBER(SEARCH("Horror", C511)), ISNUMBER(SEARCH("Thriller", C511))), "Horror or Thriller", "Other")) -> Horror or Thriller | I511: =IF(NOT(ISNUMBER(SEARCH("Comedy", C511))), "Not Comedy", "Comedy") -> Comedy | J511: =IF(F511>2020, "Recent", "Old") -> Old
A512: tt0808510 | B512: Tooth Fairy | C512: Comedy, Family, Fantasy | D512: 5 | E512: 50577 | F512: 2010 | G512: =IF(AND(D512>5, E512>1000), "Popular", "Not Popular") -> Not Popular | H512: =IF(OR(ISNUMBER(SEARCH("Action", C512)), ISNUMBER(SEARCH("Drama", C512))), "Action or Drama", IF(OR(ISNUMBER(SEARCH("Horror", C512)), ISNUMBER(SEARCH("Thriller", C512))), "Horror or Thriller", "Other")) -> Other | I512: =IF(NOT(ISNUMBER(SEARCH("Comedy", C512))), "Not Comedy", "Comedy") -> Comedy | J512: =IF(F512>2020, "Recent", "Old") -> Old
A513: tt1640571 | B513: Titanic II | C513: Action, Adventure, Drama | D513: 1.7 | E513: 13142 | F513: 2010 | G513: =IF(AND(D513>5, E513>1000), "Popular", "Not Popular") -> Not Popular | H513: =IF(OR(ISNUMBER(SEARCH("Action", C513)), ISNUMBER(SEARCH("Drama", C513))), "Action or Drama", IF(OR(ISNUMBER(SEARCH("Horror", C513)), ISNUMBER(SEARCH("Thriller", C513))), "Horror or Thriller", "Other")) -> Action or Drama | I513: =IF(NOT(ISNUMBER(SEARCH("Comedy", C513))), "Not Comedy", "Comedy") -> Not Comedy | J513: =IF(F513>2020, "Recent", "Old") -> Old
A514: tt1325004 | B514: The Twilight Saga: Eclipse | C514: Action, Adventure, Drama | D514: 5.1 | E514: 265386 | F514: 2010 | G514: =IF(AND(D514>5, E514>1000), "Popular", "Not Popular") -> Popular | H514: =IF(OR(ISNUMBER(SEARCH("Action", C514)), ISNUMBER(SEARCH("Drama", C514))), "Action or Drama", IF(OR(ISNUMBER(SEARCH("Horror", C514)), ISNUMBER(SEARCH("Thriller", C514))), "Horror or Thriller", "Other")) -> Action or Drama | I514: =IF(NOT(ISNUMBER(SEARCH("Comedy", C514))), "Not Comedy", "Comedy") -> Not Comedy | J514: =IF(F514>2020, "Recent", "Old") -> Old
A515: tt1403988 | B515: The Romantics | C515: Comedy, Drama, Romance | D515: 5 | E515: 12596 | F515: 2010 | G515: =IF(AND(D515>5, E515>1000), "Popular", "Not Popular") -> Not Popular | H515: =IF(OR(ISNUMBER(SEARCH("Action", C515)), ISNUMBER(SEARCH("Drama", C515))), "Action or Drama", IF(OR(ISNUMBER(SEARCH("Horror", C515)), ISNUMBER(SEARCH("Thriller", C515))), "Horror or Thriller", "Other")) -> Action or Drama | I515: =IF(NOT(ISNUMBER(SEARCH("Comedy", C515))), "Not Comedy", "Comedy") -> Comedy | J515: =IF(F515>2020, "Recent", "Old") -> Old
A516: tt0938283 | B516: The Last Airbender | C516: Action, Adventure, Family | D516: 4 | E516: 176827 | F516: 2010 | G516: =IF(AND(D516>5, E516>1000), "Popular", "Not Popular") -> Not Popular | H516: =IF(OR(ISNUMBER(SEARCH("Action", C516)), ISNUMBER(SEARCH("Drama", C516))), "Action or Drama", IF(OR(ISNUMBER(SEARCH("Horror", C516)), ISNUMBER(SEARCH("Thriller", C516))), "Horror or Thriller", "Other")) -> Action or Drama | I516: =IF(NOT(ISNUMBER(SEARCH("Comedy", C516))), "Not Comedy", "Comedy") -> Not Comedy | J516: =IF(F516>2020, "Recent", "Old") -> Old
A517: tt0411951 | B517: Tekken | C517: Action, Crime, Drama | D517: 4.8 | E517: 28817 | F517: 2010 | G517: =IF(AND(D517>5, E517>1000), "Popular", "Not Popular") -> Not Popular | H517: =IF(OR(ISNUMBER(SEARCH("Action", C517)), ISNUMBER(SEARCH("Drama", C517))), "Action or Drama", IF(OR(ISNUMBER(SEARCH("Horror", C517)), ISNUMBER(SEARCH("Thriller", C517))), "Horror or Thriller", "Other")) -> Action or Drama | I517: =IF(NOT(ISNUMBER(SEARCH("Comedy", C517))), "Not Comedy", "Comedy") -> Not Comedy | J517: =IF(F517>2020, "Recent", "Old") -> Old
A518: tt1572311 | B518: Tees Maar Khan | C518: Comedy, Crime | D518: 2.7 | E518: 14689 | F518: 2010 | G518: =IF(AND(D518>5, E518>1000), "Popular", "Not Popular") -> Not Popular | H518: =IF(OR(ISNUMBER(SEARCH("Action", C518)), ISNUMBER(SEARCH("Drama", C518))), "Action or Drama", IF(OR(ISNUMBER(SEARCH("Horror", C518)), ISNUMBER(SEARCH("Thriller", C518))), "Horror or Thriller", "Other")) -> Other | I518: =IF(NOT(ISNUMBER(SEARCH("Comedy", C518))), "Not Comedy", "Comedy") -> Comedy | J518: =IF(F518>2020, "Recent", "Old") -> Old
A519: tt1319743 | B519: Smokin' Aces 2: Assassins' Ball | C519: Action, Comedy, Crime | D519: 5 | E519: 14433 | F519: 2010 | G519: =IF(AND(D519>5, E519>1000), "Popular", "Not Popular") -> Not Popular | H519: =IF(OR(ISNUMBER(SEARCH("Action", C519)), ISNUMBER(SEARCH("Drama", C519))), "Action or Drama", IF(OR(ISNUMBER(SEARCH("Horror", C519)), ISNUMBER(SEARCH("Thriller", C519))), "Horror or Thriller", "Other")) -> Action or Drama | I519: =IF(NOT(ISNUMBER(SEARCH("Comedy", C519))), "Not Comedy", "Comedy") -> Comedy | J519: =IF(F519>2020, "Recent", "Old") -> Old
... A1001: tt0052077 | B1001: Plan 9 from Outer Space | C1001: Horror, Sci-Fi | D1001: 3.9 | E1001: 41105 | F1001: 1957 | G1001: =IF(AND(D1001>5, E1001>1000), "Popular", "Not Popular") -> Not Popular | H1001: =IF(OR(ISNUMBER(SEARCH("Action", C1001)), ISNUMBER(SEARCH("Drama", C1001))), "Action or Drama", IF(OR(ISNUMBER(SEARCH("Horror", C1001)), ISNUMBER(SEARCH("Thriller", C1001))), "Horror or Thriller", "Other")) -> Horror or Thriller | I1001: =IF(NOT(ISNUMBER(SEARCH("Comedy", C1001))), "Not Comedy", "Comedy") -> Not Comedy | J1001: =IF(F1001>2020, "Recent", "Old") -> Old

Sheet Chapter - 5
A1: 1) Using Vlookup to get the Genre and Release Year based on Id. 2) Sum Of Votes Per Release Year based on Genre. | L1: Which Genre Got Highest Votes Among all the Release Years?
A2: id | B2: Genre | C2: Release year(2000-2024) | D2: Sum Of Votes PerYear Based on Genre | F2: Top7 Titles in 2024 having highest votes | L2: Genres | M2: Total Votes for all Release years
A3: tt0192731 | B3: =VLOOKUP(A3, 'Raw data'!A2:F1001,3,FALSE) -> Horror, Mystery | C3: =VLOOKUP(A3,'Raw data'!A2:F1001,6,FALSE) -> 2000 | D3: =SUMIFS('Raw data'!E2:E1001, 'Raw data'!C2:C1001, B3, 'Raw data'!F2:F1001, C3) -> 19287 | F3: Title | G3: NumofVotes | H3: Genre | I3: AvgRating | L3: {=_xlfn.UNIQUE('Raw data'!C2:C1001)} -> Drama, Romance, Thriller | M3: =SUMIFS('Raw data'!E:E, 'Raw data'!C:C, L3) -> 407734
A4: tt0265087 | B4: =VLOOKUP(A4, 'Raw data'!A3:F1002,3,FALSE) -> Adventure, Comedy, Fantasy | C4: =VLOOKUP(A4,'Raw data'!A3:F1002,6,FALSE) -> 2001 | D4: =SUMIFS('Raw data'!E3:E1002, 'Raw data'!C3:C1002, B4, 'Raw data'!F3:F1002, C4) -> 43983 | F4: =INDEX('Raw data'!B2:B1001, MATCH(G4, 'Raw data'!E2:E1001, 0)) -> The Acolyte | G4: {=LARGE(IF('Raw data'!F2:F1001=2024, 'Raw data'!E2:E1001), 1)} -> 124735 | H4: =INDEX('Raw data'!C2:C1001, MATCH(F4, 'Raw data'!B2:B1001, 0)) -> Action, Adventure, Drama | I4: =INDEX('Raw data'!D2:D1001, MATCH(F4, 'Raw data'!B2:B1001, 0)) -> 4.1 | L4: Adventure, Drama, Fantasy | M4: =SUMIFS('Raw data'!E:E, 'Raw data'!C:C, L4) -> 563363
A5: tt0283632 | B5: =VLOOKUP(A5, 'Raw data'!A4:F1003,3,FALSE) -> Horror, Mystery, Thriller | C5: =VLOOKUP(A5,'Raw data'!A4:F1003,6,FALSE) -> 2002 | D5: =SUMIFS('Raw data'!E4:E1003, 'Raw data'!C4:C1003, B5, 'Raw data'!F4:F1003, C5) -> 29096 | F5: =INDEX('Raw data'!B3:B1002, MATCH(G5, 'Raw data'!E3:E1002, 0)) -> Madame Web | G5: {=LARGE(IF('Raw data'!F3:F1002=2024, 'Raw data'!E3:E1002), 2)} -> 91349 | H5: =INDEX('Raw data'!C3:C1002, MATCH(F5, 'Raw data'!B3:B1002, 0)) -> Action, Adventure, Sci-Fi | I5: =INDEX('Raw data'!D3:D1002, MATCH(F5, 'Raw data'!B3:B1002, 0)) -> 4 | L5: Action, Sci-Fi | M5: =SUMIFS('Raw data'!E:E, 'Raw data'!C:C, L5) -> 464662
A6: tt0313911 | B6: =VLOOKUP(A6, 'Raw data'!A5:F1004,3,FALSE) -> Action, Adventure, Comedy | C6: =VLOOKUP(A6,'Raw data'!A5:F1004,6,FALSE) -> 2003 | D6: =SUMIFS('Raw data'!E5:E1004, 'Raw data'!C5:C1004, B6, 'Raw data'!F5:F1004, C6) -> 274028 | F6: =INDEX('Raw data'!B4:B1003, MATCH(G6, 'Raw data'!E4:E1003, 0)) -> Indian Police Force | G6: {=LARGE(IF('Raw data'!F4:F1003=2024, 'Raw data'!E4:E1003), 3)} -> 58338 | H6: =INDEX('Raw data'!C4:C1003, MATCH(F6, 'Raw data'!B4:B1003, 0)) -> Action, Crime, Drama | I6: =INDEX('Raw data'!D4:D1003, MATCH(F6, 'Raw data'!B4:B1003, 0)) -> 4.9 | L6: Action, Adventure, Drama | M6: =SUMIFS('Raw data'!E:E, 'Raw data'!C:C, L6) -> 1341014
A7: tt0365957 | B7: =VLOOKUP(A7, 'Raw data'!A6:F1005,3,FALSE) -> Drama, Music | C7: =VLOOKUP(A7,'Raw data'!A6:F1005,6,FALSE) -> 2004 | D7: =SUMIFS('Raw data'!E6:E1005, 'Raw data'!C6:C1005, B7, 'Raw data'!F6:F1005, C7) -> 28830 | F7: =INDEX('Raw data'!B5:B1004, MATCH(G7, 'Raw data'!E5:E1004, 0)) -> Bade Miyan Chote Miyan | G7: {=LARGE(IF('Raw data'!F5:F1004=2024, 'Raw data'!E5:E1004), 4)} -> 38451 | H7: =INDEX('Raw data'!C5:C1004, MATCH(F7, 'Raw data'!B5:B1004, 0)) -> Action, Adventure, Sci-Fi | I7: =INDEX('Raw data'!D5:D1004, MATCH(F7, 'Raw data'!B5:B1004, 0)) -> 3.9 | L7: Adventure, Drama, Sci-Fi | M7: =SUMIFS('Raw data'!E:E, 'Raw data'!C:C, L7) -> 277533
A8: tt0808146 | B8: =VLOOKUP(A8, 'Raw data'!A7:F1006,3,FALSE) -> Comedy | C8: =VLOOKUP(A8,'Raw data'!A7:F1006,6,FALSE) -> 2006 | D8: =SUMIFS('Raw data'!E7:E1006, 'Raw data'!C7:C1006, B8, 'Raw data'!F7:F1006, C8) -> 225590 | F8: =INDEX('Raw data'!B6:B1005, MATCH(G8, 'Raw data'!E6:E1005, 0)) -> Martin | G8: {=LARGE(IF('Raw data'!F6:F1005=2024, 'Raw data'!E6:E1005), 5)} -> 34529 | H8: =INDEX('Raw data'!C6:C1005, MATCH(F8, 'Raw data'!B6:B1005, 0)) -> Action, Drama, Thriller | I8: =INDEX('Raw data'!D6:D1005, MATCH(F8, 'Raw data'!B6:B1005, 0)) -> 4.5 | L8: Action, Thriller | M8: =SUMIFS('Raw data'!E:E, 'Raw data'!C:C, L8) -> 564710
A9: tt0785077 | B9: =VLOOKUP(A9, 'Raw data'!A8:F1007,3,FALSE) -> Comedy, Sport | C9: =VLOOKUP(A9,'Raw data'!A8:F1007,6,FALSE) -> 2007 | D9: =SUMIFS('Raw data'!E8:E1007, 'Raw data'!C8:C1007, B9, 'Raw data'!F8:F1007, C9) -> 42021 | F9: =INDEX('Raw data'!B7:B1006, MATCH(G9, 'Raw data'!E7:E1006, 0)) -> Under Paris | G9: {=LARGE(IF('Raw data'!F7:F1006=2024, 'Raw data'!E7:E1006), 6)} -> 32479 | H9: =INDEX('Raw data'!C7:C1006, MATCH(F9, 'Raw data'!B7:B1006, 0)) -> Action, Drama, Horror | I9: =INDEX('Raw data'!D7:D1006, MATCH(F9, 'Raw data'!B7:B1006, 0)) -> 5.2 | L9: Action, Adventure, Sci-Fi | M9: =SUMIFS('Raw data'!E:E, 'Raw data'!C:C, L9) -> 1574437
A10: tt0443649 | B10: =VLOOKUP(A10, 'Raw data'!A9:F1008,3,FALSE) -> Action, Adventure, Drama | C10: =VLOOKUP(A10,'Raw data'!A9:F1008,6,FALSE) -> 2008 | D10: =SUMIFS('Raw data'!E9:E1008, 'Raw data'!C9:C1008, B10, 'Raw data'!F9:F1008, C10) -> 136533 | F10: =INDEX('Raw data'!B8:B1007, MATCH(G10, 'Raw data'!E8:E1007, 0)) -> Borderlands | G10: {=LARGE(IF('Raw data'!F8:F1007=2024, 'Raw data'!E8:E1007), 7)} -> 31263 | H10: =INDEX('Raw data'!C8:C1007, MATCH(F10, 'Raw data'!B8:B1007, 0)) -> Action, Adventure, Comedy | I10: =INDEX('Raw data'!D8:D1007, MATCH(F10, 'Raw data'!B8:B1007, 0)) -> 4.6 | L10: Action, Adventure, Comedy | M10: =SUMIFS('Raw data'!E:E, 'Raw data'!C:C, L10) -> 1636625
A11: tt1045778 | B11: =VLOOKUP(A11, 'Raw data'!A10:F1009,3,FALSE) -> Comedy | C11: =VLOOKUP(A11,'Raw data'!A10:F1009,6,FALSE) -> 2009 | D11: =SUMIFS('Raw data'!E10:E1009, 'Raw data'!C10:C1009, B11, 'Raw data'!F10:F1009, C11) -> 190898 | L11: Action, Crime, Thriller | M11: =SUMIFS('Raw data'!E:E, 'Raw data'!C:C, L11) -> 518203
A12: tt1320304 | B12: =VLOOKUP(A12, 'Raw data'!A11:F1010,3,FALSE) -> Horror, Thriller | C12: =VLOOKUP(A12,'Raw data'!A11:F1010,6,FALSE) -> 2010 | D12: =SUMIFS('Raw data'!E11:E1010, 'Raw data'!C11:C1010, B12, 'Raw data'!F11:F1010, C12) -> 40360 | F12: Genre: Top 7 Largest Sum of Votes among All Release Years | L12: Action, Adventure, Family | M12: =SUMIFS('Raw data'!E:E, 'Raw data'!C:C, L12) -> 344294
A13: tt1788979 | B13: =VLOOKUP(A13, 'Raw data'!A12:F1011,3,FALSE) -> Crime, Thriller | C13: =VLOOKUP(A13,'Raw data'!A12:F1011,6,FALSE) -> 2011 | D13: =SUMIFS('Raw data'!E12:E1011, 'Raw data'!C12:C1011, B13, 'Raw data'!F12:F1011, C13) -> 34925 | F13: Genre | G13: Top 7 Vote Counts | L13: Action, Adventure, Fantasy | M13: =SUMIFS('Raw data'!E:E, 'Raw data'!C:C, L13) -> 845644
A14: tt2375779 | B14: =VLOOKUP(A14, 'Raw data'!A13:F1012,3,FALSE) -> Adventure, Horror | C14: =VLOOKUP(A14,'Raw data'!A13:F1012,6,FALSE) -> 2012 | D14: =SUMIFS('Raw data'!E13:E1012, 'Raw data'!C13:C1012, B14, 'Raw data'!F13:F1012, C14) -> 23717 | F14: =INDEX(L$3:L$196, MATCH(LARGE(M$3:M$196, 1), M$3:M$196, 0)) -> Comedy | G14: =LARGE(M$3:M$196, 1) -> 1719522 | L14: Action, Comedy, Sci-Fi | M14: =SUMIFS('Raw data'!E:E, 'Raw data'!C:C, L14) -> 339253
A15: tt1606378 | B15: =VLOOKUP(A15, 'Raw data'!A9:F1013,3,FALSE) -> Action, Thriller | C15: =VLOOKUP(A15,'Raw data'!A9:F1013,6,FALSE) -> 2013 | D15: =SUMIFS('Raw data'!E14:E1013, 'Raw data'!C14:C1013, B15, 'Raw data'!F14:F1013, C15) -> 25450 | F15: =INDEX(L$3:L$196, MATCH(LARGE(M$3:M$196, 2), M$3:M$196, 0)) -> Action, Adventure, Comedy | G15: =LARGE(M$3:M$196, 2) -> 1636625 | L15: Action, Adventure, Horror | M15: =SUMIFS('Raw data'!E:E, 'Raw data'!C:C, L15) -> 598575
A16: tt2784512 | B16: =VLOOKUP(A16, 'Raw data'!A15:F1014,3,FALSE) -> Comedy, Horror | C16: =VLOOKUP(A16,'Raw data'!A15:F1014,6,FALSE) -> 2014 | D16: =SUMIFS('Raw data'!E15:E1014, 'Raw data'!C15:C1014, B16, 'Raw data'!F15:F1014, C16) -> 21038 | F16: =INDEX(L$3:L$196, MATCH(LARGE(M$3:M$196, 3), M$3:M$196, 0)) -> Action, Adventure, Sci-Fi | G16: =LARGE(M$3:M$196, 3) -> 1574437 | L16: Action, Horror, Sci-Fi | M16: =SUMIFS('Raw data'!E:E, 'Raw data'!C:C, L16) -> 729929
A17: tt3774790 | B17: =VLOOKUP(A17, 'Raw data'!A16:F1015,3,FALSE) -> Mystery, Sci-Fi, Thriller | C17: =VLOOKUP(A17,'Raw data'!A16:F1015,6,FALSE) -> 2015 | D17: =SUMIFS('Raw data'!E16:E1015, 'Raw data'!C16:C1015, B17, 'Raw data'!F16:F1015, C17) -> 11349 | F17: =INDEX(L$3:L$196, MATCH(LARGE(M$3:M$196, 4), M$3:M$196, 0)) -> Horror, Mystery, Thriller | G17: =LARGE(M$3:M$196, 4) -> 1377044 | L17: Comedy | M17: =SUMIFS('Raw data'!E:E, 'Raw data'!C:C, L17) -> 1719522
A18: tt1608290 | B18: =VLOOKUP(A18, 'Raw data'!A17:F1016,3,FALSE) -> Action, Adventure, Comedy | C18: =VLOOKUP(A18,'Raw data'!A17:F1016,6,FALSE) -> 2016 | D18: =SUMIFS('Raw data'!E17:E1016, 'Raw data'!C17:C1016, B18, 'Raw data'!F17:F1016, C18) -> 77401 | F18: =INDEX(L$3:L$196, MATCH(LARGE(M$3:M$196, 5), M$3:M$196, 0)) -> Action, Adventure, Drama | G18: =LARGE(M$3:M$196, 5) -> 1341014 | L18: Action, Comedy, Crime | M18: =SUMIFS('Raw data'!E:E, 'Raw data'!C:C, L18) -> 882591
A19: tt1935897 | B19: =VLOOKUP(A19, 'Raw data'!A18:F1017,3,FALSE) -> Horror, Thriller | C19: =VLOOKUP(A19,'Raw data'!A18:F1017,6,FALSE) -> 2017 | D19: =SUMIFS('Raw data'!E18:E1017, 'Raw data'!C18:C1017, B19, 'Raw data'!F18:F1017, C19) -> 30154 | F19: =INDEX(L$3:L$196, MATCH(LARGE(M$3:M$196, 6), M$3:M$196, 0)) -> Horror, Thriller | G19: =LARGE(M$3:M$196, 6) -> 1085481 | L19: Action, Fantasy, Thriller | M19: =SUMIFS('Raw data'!E:E, 'Raw data'!C:C, L19) -> 128358
A20: tt5842616 | B20: =VLOOKUP(A20, 'Raw data'!A19:F1018,3,FALSE) -> Comedy | C20: =VLOOKUP(A20,'Raw data'!A19:F1018,6,FALSE) -> 2018 | D20: =SUMIFS('Raw data'!E19:E1018, 'Raw data'!C19:C1018, B20, 'Raw data'!F19:F1018, C20) -> 92272 | F20: =INDEX(L$3:L$196, MATCH(LARGE(M$3:M$196, 7), M$3:M$196, 0)) -> Adventure, Comedy, Family | G20: =LARGE(M$3:M$196, 7) -> 1013081 | L20: Action, Crime, Fantasy | M20: =SUMIFS('Raw data'!E:E, 'Raw data'!C:C, L20) -> 276390
A21: tt7329656 | B21: =VLOOKUP(A21, 'Raw data'!A20:F1019,3,FALSE) -> Adventure, Drama, Horror | C21: =VLOOKUP(A21,'Raw data'!A20:F1019,6,FALSE) -> 2019 | D21: =SUMIFS('Raw data'!E20:E1019, 'Raw data'!C20:C1019, B21, 'Raw data'!F20:F1019, C21) -> 31684 | L21: Comedy, Romance | M21: =SUMIFS('Raw data'!E:E, 'Raw data'!C:C, L21) -> 837880
A22: tt10600398 | B22: =VLOOKUP(A22, 'Raw data'!A21:F1020,3,FALSE) -> Action, Animation, Comedy | C22: =VLOOKUP(A22,'Raw data'!A21:F1020,6,FALSE) -> 2020 | D22: =SUMIFS('Raw data'!E21:E1020, 'Raw data'!C21:C1020, B22, 'Raw data'!F21:F1020, C22) -> 17665 | F22: Top 5 Genre Having highest Votes and Their Release Year | L22: Horror, Thriller | M22: =SUMIFS('Raw data'!E:E, 'Raw data'!C:C, L22) -> 1085481
A23: tt14878948 | B23: =VLOOKUP(A23, 'Raw data'!A22:F1021,3,FALSE) -> Action, Drama, War | C23: =VLOOKUP(A23,'Raw data'!A22:F1021,6,FALSE) -> 2021 | D23: =SUMIFS('Raw data'!E22:E1021, 'Raw data'!C22:C1021, B23, 'Raw data'!F22:F1021, C23) -> 20687 | F23: Genre | G23: Release Year | H23: Highest Vote Count | L23: Drama, Mystery, Romance | M23: =SUMIFS('Raw data'!E:E, 'Raw data'!C:C, L23) -> 248427
A24: tt13235822 | B24: =VLOOKUP(A24, 'Raw data'!A23:F1022,3,FALSE) -> Drama, Horror, Mystery | C24: =VLOOKUP(A24,'Raw data'!A23:F1022,6,FALSE) -> 2022 | D24: =SUMIFS('Raw data'!E23:E1022, 'Raw data'!C23:C1022, B24, 'Raw data'!F23:F1022, C24) -> 99277 | F24: =INDEX($B$2:$B$54, MATCH(H24, $D$2:$D$54, 0)) -> Action, Adventure, Comedy | G24: =INDEX($C$2:$C$54, MATCH(H24, $D$2:$D$54, 0)) -> 2003 | H24: =LARGE($D$2:$D$54, 1) -> 274028 | L24: Drama, Music | M24: =SUMIFS('Raw data'!E:E, 'Raw data'!C:C, L24) -> 141466
A25: tt12915716 | B25: =VLOOKUP(A25, 'Raw data'!A24:F1023,3,FALSE) -> Action, Adventure, Drama | C25: =VLOOKUP(A25,'Raw data'!A24:F1023,6,FALSE) -> 2023 | D25: =SUMIFS('Raw data'!E24:E1023, 'Raw data'!C24:C1023, B25, 'Raw data'!F24:F1023, C25) -> 172067 | F25: =INDEX($B$2:$B$54, MATCH(H25, $D$2:$D$54, 0)) -> Comedy | G25: =INDEX($C$2:$C$54, MATCH(H25, $D$2:$D$54, 0)) -> 2006 | H25: =LARGE($D$2:$D$54, 2) -> 225590 | L25: Comedy, Fantasy | M25: =SUMIFS('Raw data'!E:E, 'Raw data'!C:C, L25) -> 165658
A26: tt13964390 | B26: =VLOOKUP(A26, 'Raw data'!A25:F1024,3,FALSE) -> Action, Drama, Horror | C26: =VLOOKUP(A26,'Raw data'!A25:F1024,6,FALSE) -> 2024 | D26: =SUMIFS('Raw data'!E25:E1024, 'Raw data'!C25:C1024, B26, 'Raw data'!F25:F1024, C26) -> 32479 | F26: =INDEX($B$2:$B$54, MATCH(H26, $D$2:$D$54, 0)) -> Comedy | G26: =INDEX($C$2:$C$54, MATCH(H26, $D$2:$D$54, 0)) -> 2009 | H26: =LARGE($D$2:$D$54, 3) -> 190898 | L26: Adventure, Comedy, Fantasy | M26: =SUMIFS('Raw data'!E:E, 'Raw data'!C:C, L26) -> 206207
F27: =INDEX($B$2:$B$54, MATCH(H27, $D$2:$D$54, 0)) -> Action, Adventure, Drama | G27: =INDEX($C$2:$C$54, MATCH(H27, $D$2:$D$54, 0)) -> 2023 | H27: =LARGE($D$2:$D$54, 4) -> 172067 | L27: Crime, Drama, Horror | M27: =SUMIFS('Raw data'!E:E, 'Raw data'!C:C, L27) -> 149690
F28: =INDEX($B$2:$B$54, MATCH(H28, $D$2:$D$54, 0)) -> Action, Adventure, Drama | G28: =INDEX($C$2:$C$54, MATCH(H28, $D$2:$D$54, 0)) -> 2008 | H28: =LARGE($D$2:$D$54, 5) -> 136533 | L28: Crime, Thriller | M28: =SUMIFS('Raw data'!E:E, 'Raw data'!C:C, L28) -> 158658
L29: Drama, Romance | M29: =SUMIFS('Raw data'!E:E, 'Raw data'!C:C, L29) -> 324515
F30: Total Votes from 2021-24 based on Genre | L30: Action, Adventure, Crime | M30: =SUMIFS('Raw data'!E:E, 'Raw data'!C:C, L30) -> 375823
F31: Genre | G31: Total Votes In 2021 | H31: Total Votes In 2022 | I31: Total Votes In 2023 | J31: Total Votes In 2024 | L31: Action, Adventure, Thriller | M31: =SUMIFS('Raw data'!E:E, 'Raw data'!C:C, L31) -> 198737
F32: Comedy | G32: =SUMIFS('Raw data'!E2:E1001, 'Raw data'!F2:F1001,2021, 'Raw data'!C2:C1001, F32) -> 0 | H32: =SUMIFS('Raw data'!E2:E1001, 'Raw data'!F2:F1001, 2022, 'Raw data'!C2:C1001, F32) -> 71074 | I32: =SUMIFS('Raw data'!E2:E1001, 'Raw data'!F2:F1001, 2023, 'Raw data'!C2:C1001, F32) -> 0 | J32: =SUMIFS('Raw data'!E2:E1001, 'Raw data'!F2:F1001, 2024, 'Raw data'!C2:C1001, F32) -> 0 | L32: Adventure, Comedy, Family | M32: =SUMIFS('Raw data'!E:E, 'Raw data'!C:C, L32) -> 1013081
F33: Action, Adventure, Comedy | G33: =SUMIFS('Raw data'!E3:E1002, 'Raw data'!F3:F1002,2021, 'Raw data'!C3:C1002, F33) -> 60406 | H33: =SUMIFS('Raw data'!E3:E1002, 'Raw data'!F3:F1002, 2022, 'Raw data'!C3:C1002, F33) -> 208770 | I33: =SUMIFS('Raw data'!E3:E1002, 'Raw data'!F3:F1002, 2023, 'Raw data'!C3:C1002, F33) -> 0 | J33: =SUMIFS('Raw data'!E3:E1002, 'Raw data'!F3:F1002, 2024, 'Raw data'!C3:C1002, F33) -> 31263 | L33: Action, Drama | M33: =SUMIFS('Raw data'!E:E, 'Raw data'!C:C, L33) -> 176512
F34: Action, Adventure, Sci-Fi | G34: =SUMIFS('Raw data'!E4:E1003, 'Raw data'!F4:F1003,2021, 'Raw data'!C4:C1003, F34) -> 0 | H34: =SUMIFS('Raw data'!E4:E1003, 'Raw data'!F4:F1003, 2022, 'Raw data'!C4:C1003, F34) -> 103225 | I34: =SUMIFS('Raw data'!E4:E1003, 'Raw data'!F4:F1003, 2023, 'Raw data'!C4:C1003, F34) -> 0 | J34: =SUMIFS('Raw data'!E4:E1003, 'Raw data'!F4:F1003, 2024, 'Raw data'!C4:C1003, F34) -> 129800 | L34: Drama | M34: =SUMIFS('Raw data'!E:E, 'Raw data'!C:C, L34) -> 327340
F35: Horror, Mystery, Thriller | G35: =SUMIFS('Raw data'!E5:E1004, 'Raw data'!F5:F1004,2021, 'Raw data'!C5:C1004, F35) -> 91525 | H35: =SUMIFS('Raw data'!E5:E1004, 'Raw data'!F5:F1004, 2022, 'Raw data'!C5:C1004, F35) -> 15339 | I35: =SUMIFS('Raw data'!E5:E1004, 'Raw data'!F5:F1004, 2023, 'Raw data'!C5:C1004, F35) -> 0 | J35: =SUMIFS('Raw data'!E5:E1004, 'Raw data'!F5:F1004, 2024, 'Raw data'!C5:C1004, F35) -> 15023 | L35: Comedy, Sci-Fi | M35: =SUMIFS('Raw data'!E:E, 'Raw data'!C:C, L35) -> 173196
F36: Action, Adventure, Drama | G36: =SUMIFS('Raw data'!E6:E1005, 'Raw data'!F6:F1005,2021, 'Raw data'!C6:C1005, F36) -> 26968 | H36: =SUMIFS('Raw data'!E6:E1005, 'Raw data'!F6:F1005, 2022, 'Raw data'!C6:C1005, F36) -> 131192 | I36: =SUMIFS('Raw data'!E6:E1005, 'Raw data'!F6:F1005, 2023, 'Raw data'!C6:C1005, F36) -> 172067 | J36: =SUMIFS('Raw data'!E6:E1005, 'Raw data'!F6:F1005, 2024, 'Raw data'!C6:C1005, F36) -> 243324 | L36: Action, Sci-Fi, Thriller | M36: =SUMIFS('Raw data'!E:E, 'Raw data'!C:C, L36) -> 241930
F37: Horror, Thriller | G37: =SUMIFS('Raw data'!E7:E1006, 'Raw data'!F7:F1006,2021, 'Raw data'!C7:C1006, F37) -> 0 | H37: =SUMIFS('Raw data'!E7:E1006, 'Raw data'!F7:F1006, 2022, 'Raw data'!C7:C1006, F37) -> 10942 | I37: =SUMIFS('Raw data'!E7:E1006, 'Raw data'!F7:F1006, 2023, 'Raw data'!C7:C1006, F37) -> 0 | J37: =SUMIFS('Raw data'!E7:E1006, 'Raw data'!F7:F1006, 2024, 'Raw data'!C7:C1006, F37) -> 44373 | L37: Crime, Drama, Fantasy | M37: =SUMIFS('Raw data'!E:E, 'Raw data'!C:C, L37) -> 142545
F38: Adventure, Comedy, Family | G38: =SUMIFS('Raw data'!E8:E1007, 'Raw data'!F8:F1007,2021, 'Raw data'!C8:C1007, F38) -> 0 | H38: =SUMIFS('Raw data'!E8:E1007, 'Raw data'!F8:F1007, 2022, 'Raw data'!C8:C1007, F38) -> 0 | I38: =SUMIFS('Raw data'!E8:E1007, 'Raw data'!F8:F1007, 2023, 'Raw data'!C8:C1007, F38) -> 10876 | J38: =SUMIFS('Raw data'!E8:E1007, 'Raw data'!F8:F1007, 2024, 'Raw data'!C8:C1007, F38) -> 0 | L38: Horror | M38: =SUMIFS('Raw data'!E:E, 'Raw data'!C:C, L38) -> 652208
L39: Comedy, Family, Fantasy | M39: =SUMIFS('Raw data'!E:E, 'Raw data'!C:C, L39) -> 490679
L40: Documentary, Drama, History | M40: =SUMIFS('Raw data'!E:E, 'Raw data'!C:C, L40) -> 109008
L41: Comedy, Drama, Romance | M41: =SUMIFS('Raw data'!E:E, 'Raw data'!C:C, L41) -> 483017
L42: Action, Fantasy, Sci-Fi | M42: =SUMIFS('Raw data'!E:E, 'Raw data'!C:C, L42) -> 170503
L43: Action, Drama, Mystery | M43: =SUMIFS('Raw data'!E:E, 'Raw data'!C:C, L43) -> 84009
L44: Adventure, Animation, Comedy | M44: =SUMIFS('Raw data'!E:E, 'Raw data'!C:C, L44) -> 354014
L45: Fantasy, Horror, Mystery | M45: =SUMIFS('Raw data'!E:E, 'Raw data'!C:C, L45) -> 248414
L46: Horror, Mystery, Thriller | M46: =SUMIFS('Raw data'!E:E, 'Raw data'!C:C, L46) -> 1377044
L47: Comedy, Horror | M47: =SUMIFS('Raw data'!E:E, 'Raw data'!C:C, L47) -> 295452
L48: Documentary, Music | M48: =SUMIFS('Raw data'!E:E, 'Raw data'!C:C, L48) -> 131774
L49: Comedy, Fantasy, Romance | M49: =SUMIFS('Raw data'!E:E, 'Raw data'!C:C, L49) -> 76235
L50: Drama, Horror, Mystery | M50: =SUMIFS('Raw data'!E:E, 'Raw data'!C:C, L50) -> 430661
... L196: Talk-Show | M196: =SUMIFS('Raw data'!E:E, 'Raw data'!C:C, L196) -> 10099

Sheet Chapter-6
B1: An Assumption if the Old Movies in the period 1960-70 needs to be digitalized by some xx Company. They need money to do this and will look at different ways to get it. By analysing at what budget, How many can be digitalized, we can figure out how much more they might get After digitalizing if we sell to Movie platforms like Netflix or Prime. . This analysis will help them decide if digitalization the old movies is a good idea financially.
B3: Analyzing Investment Options for Old Movies Digitilazation
B4: Financial Options | C4: Period Per Year | D4: Annual Interest Rate | E4: Duration in Years | F4: Periodic Payment (PMT) | G4: Present Value (PV) | H4: Future Value(FV)
B5: Loan | C5: 6 | D5: 0.05 | E5: 5 | F5: =PMT(D5/C5,E5*C5,G5,H5) -> -32139.699 | G5: 850000
B6: Emergency Fund | C6: 12 | D6: 0.03 | E6: 3 | F6: -7497 | G6: 600000 | H6: =FV(D6/C6,E6*C6,F6,G6) -> -374389.5
B7: Delay Project | C7: 7 | D7: 0.02 | E7: 1 | G7: =PV(D7/C7,C7*E7,F7,H7) -> -49011.331 | H7: 50000
B10: Amortization Table Loan
B11: Original Loan | C11: 250000
B12: Annual Interest Rate | C12: 0.06
B13: Loan Duration in Years | C13: 3
B14: Number of Periods per Year | C14: 5
B15: Ending Value of Loan | C15: 0
B17: Quarterly Payment | C17: =PMT(C12/C14,C14*C13,C11,C15) -> -18311.176
B19: Periods | C19: Remaining Principal | D19: Interest Payment | E19: Principal Payment | F19: Ending Balance
B20: 1 | C20: =C11 -> 250000 | D20: =IPMT($C$12/$C$14, B20, $C$13*$C$14,-$C$11,,0) -> 3000 | E20: =PPMT($C$12/$C$14, B20, $C$13*$C$14, -$C$11,,0) -> 15311.176 | F20: =C20-E20 -> 234688.82
B21: 2 | C21: =F20 -> 234688.82 | D21: =IPMT($C$12/$C$14, B21, $C$13*$C$14,-$C$11,,0) -> 2816.2659 | E21: =PPMT($C$12/$C$14, B21, $C$13*$C$14, -$C$11,,0) -> 15494.91 | F21: =C21-E21 -> 219193.91
B22: 3 | C22: =F21 -> 219193.91 | D22: =IPMT($C$12/$C$14, B22, $C$13*$C$14,-$C$11,,0) -> 2630.327 | E22: =PPMT($C$12/$C$14, B22, $C$13*$C$14, -$C$11,,0) -> 15680.849 | F22: =C22-E22 -> 203513.06
B23: 4 | C23: =F22 -> 203513.06 | D23: =IPMT($C$12/$C$14, B23, $C$13*$C$14,-$C$11,,0) -> 2442.1568 | E23: =PPMT($C$12/$C$14, B23, $C$13*$C$14, -$C$11,,0) -> 15869.019 | F23: =C23-E23 -> 187644.05
B24: 5 | C24: =F23 -> 187644.05 | D24: =IPMT($C$12/$C$14, B24, $C$13*$C$14,-$C$11,,0) -> 2251.7285 | E24: =PPMT($C$12/$C$14, B24, $C$13*$C$14, -$C$11,,0) -> 16059.448 | F24: =C24-E24 -> 171584.6
B25: 6 | C25: =F24 -> 171584.6 | D25: =IPMT($C$12/$C$14, B25, $C$13*$C$14,-$C$11,,0) -> 2059.0152 | E25: =PPMT($C$12/$C$14, B25, $C$13*$C$14, -$C$11,,0) -> 16252.161 | F25: =C25-E25 -> 155332.44
B26: 7 | C26: =F25 -> 155332.44 | D26: =IPMT($C$12/$C$14, B26, $C$13*$C$14,-$C$11,,0) -> 1863.9892 | E26: =PPMT($C$12/$C$14, B26, $C$13*$C$14, -$C$11,,0) -> 16447.187 | F26: =C26-E26 -> 138885.25
B27: 8 | C27: =F26 -> 138885.25 | D27: =IPMT($C$12/$C$14, B27, $C$13*$C$14,-$C$11,,0) -> 1666.623 | E27: =PPMT($C$12/$C$14, B27, $C$13*$C$14, -$C$11,,0) -> 16644.553 | F27: =C27-E27 -> 122240.7
B28: 9 | C28: =F27 -> 122240.7 | D28: =IPMT($C$12/$C$14, B28, $C$13*$C$14,-$C$11,,0) -> 1466.8884 | E28: =PPMT($C$12/$C$14, B28, $C$13*$C$14, -$C$11,,0) -> 16844.288 | F28: =C28-E28 -> 105396.41
B29: 10 | C29: =F28 -> 105396.41 | D29: =IPMT($C$12/$C$14, B29, $C$13*$C$14,-$C$11,,0) -> 1264.7569 | E29: =PPMT($C$12/$C$14, B29, $C$13*$C$14, -$C$11,,0) -> 17046.419 | F29: =C29-E29 -> 88349.989
B30: 11 | C30: =F29 -> 88349.989 | D30: =IPMT($C$12/$C$14, B30, $C$13*$C$14,-$C$11,,0) -> 1060.1999 | E30: =PPMT($C$12/$C$14, B30, $C$13*$C$14, -$C$11,,0) -> 17250.976 | F30: =C30-E30 -> 71099.013
B31: 12 | C31: =F30 -> 71099.013 | D31: =IPMT($C$12/$C$14, B31, $C$13*$C$14,-$C$11,,0) -> 853.18816 | E31: =PPMT($C$12/$C$14, B31, $C$13*$C$14, -$C$11,,0) -> 17457.988 | F31: =C31-E31 -> 53641.025
B32: 13 | C32: =F31 -> 53641.025 | D32: =IPMT($C$12/$C$14, B32, $C$13*$C$14,-$C$11,,0) -> 643.6923 | E32: =PPMT($C$12/$C$14, B32, $C$13*$C$14, -$C$11,,0) -> 17667.484 | F32: =C32-E32 -> 35973.541
... B34: 15 | C34: =F33 -> 18094.048 | D34: =IPMT($C$12/$C$14, B34, $C$13*$C$14,-$C$11,,0) -> 217.12857 | E34: =PPMT($C$12/$C$14, B34, $C$13*$C$14, -$C$11,,0) -> 18094.048 | F34: =C34-E34 -> 0

Sheet Chapter -7
A1: title | B1: genres | C1: averageRating | D1: numVotes | E1: releaseYear | F1: TRIM and CONCAT
A2: Plan 9 from Outer Space | B2: Horror, Sci-Fi | C2: 3.9 | D2: 41105 | E2: 1957 | F2: =_xlfn.CONCAT(TRIM(A2)," ", ": Rating"," ",C2,","," ","Released in", " ",E2) -> Plan 9 from Outer Space : Rating 3.9, Released in 1957
A3: The Beast of Yucca Flats | B3: Horror, Sci-Fi | C3: 1.9 | D3: 10499 | E3: 1961 | F3: =_xlfn.CONCAT(TRIM(A3)," ", ": Rating"," ",C3,","," ","Released in", " ",E3) -> The Beast of Yucca Flats : Rating 1.9, Released in 1961
A4: Santa Claus Conquers the Martians | B4: Adventure, Comedy, Family | C4: 2.7 | D4: 12767 | E4: 1964 | F4: =_xlfn.CONCAT(TRIM(A4)," ", ": Rating"," ",C4,","," ","Released in", " ",E4) -> Santa Claus Conquers the Martians : Rating 2.7, Released in 1964
A5: Monster a Go-Go | B5: Horror, Sci-Fi | C5: 1.8 | D5: 10108 | E5: 1965 | F5: =_xlfn.CONCAT(TRIM(A5)," ", ": Rating"," ",C5,","," ","Released in", " ",E5) -> Monster a Go-Go : Rating 1.8, Released in 1965
A6: Manos: The Hands of Fate | B6: Horror | C6: 1.7 | D6: 37830 | E6: 1966 | F6: =_xlfn.CONCAT(TRIM(A6)," ", ": Rating"," ",C6,","," ","Released in", " ",E6) -> Manos: The Hands of Fate : Rating 1.7, Released in 1966
A7: Casino Royale | B7: Comedy | C7: 5 | D7: 33071 | E7: 1967 | F7: =_xlfn.CONCAT(TRIM(A7)," ", ": Rating"," ",C7,","," ","Released in", " ",E7) -> Casino Royale : Rating 5, Released in 1967
A8: Hercules in New York | B8: Adventure, Comedy, Fantasy | C8: 3.3 | D8: 19892 | E8: 1970 | F8: =_xlfn.CONCAT(TRIM(A8)," ", ": Rating"," ",C8,","," ","Released in", " ",E8) -> Hercules in New York : Rating 3.3, Released in 1970
A9: Exorcist II: The Heretic | B9: Horror | C9: 3.8 | D9: 29122 | E9: 1977 | F9: =_xlfn.CONCAT(TRIM(A9)," ", ": Rating"," ",C9,","," ","Released in", " ",E9) -> Exorcist II: The Heretic : Rating 3.8, Released in 1977
A10: The Star Wars Holiday Special | B10: Adventure, Family, Musical | C10: 2.2 | D10: 17278 | E10: 1978 | F10: =_xlfn.CONCAT(TRIM(A10)," ", ": Rating"," ",C10,","," ","Released in", " ",E10) -> The Star Wars Holiday Special : Rating 2.2, Released in 1978
A11: Attack of the Killer Tomatoes! | B11: Adventure, Comedy, Horror | C11: 4.6 | D11: 15311 | E11: 1978 | F11: =_xlfn.CONCAT(TRIM(A11)," ", ": Rating"," ",C11,","," ","Released in", " ",E11) -> Attack of the Killer Tomatoes! : Rating 4.6, Released in 1978
A12: Saturn 3 | B12: Adventure, Horror, Sci-Fi | C12: 5.1 | D12: 10769 | E12: 1980 | F12: =_xlfn.CONCAT(TRIM(A12)," ", ": Rating"," ",C12,","," ","Released in", " ",E12) -> Saturn 3 : Rating 5.1, Released in 1980
A13: Cannibal Ferox | B13: Adventure, Horror | C13: 5.1 | D13: 11052 | E13: 1981 | F13: =_xlfn.CONCAT(TRIM(A13)," ", ": Rating"," ",C13,","," ","Released in", " ",E13) -> Cannibal Ferox : Rating 5.1, Released in 1981
... A533: 67th Street, New York, NY | B533: Crime, Thriller | C533: 2.9 | D533: 34925 | E533: 2011 | F533: =_xlfn.CONCAT(TRIM(A533)," ", ": Rating"," ",C533,","," ","Released in", " ",E533) -> 67th Street, New York, NY : Rating 2.9, Released in 2011
A534: 40858 | B534: Horror, Mystery, Thriller | C534: 3.9 | D534: 12653 | E534: 2011 | F534: =_xlfn.CONCAT(TRIM(A534)," ", ": Rating"," ",C534,","," ","Released in", " ",E534) -> 40858 : Rating 3.9, Released in 2011
A535: Wrong Turn 5: Bloodlines | B535: Adventure, Horror | C535: 4.1 | D535: 23717 | E535: 2012 | F535: =_xlfn.CONCAT(TRIM(A535)," ", ": Rating"," ",C535,","," ","Released in", " ",E535) -> Wrong Turn 5: Bloodlines : Rating 4.1, Released in 2012
A536: Universal Soldier: Day of Reckoning | B536: Action, Horror, Mystery | C536: 5.1 | D536: 21613 | E536: 2012 | F536: =_xlfn.CONCAT(TRIM(A536)," ", ": Rating"," ",C536,","," ","Released in", " ",E536) -> Universal Soldier: Day of Reckoning : Rating 5.1, Released in 2012
A537: The Three Stooges | B537: Comedy, Family | C537: 5.1 | D537: 33518 | E537: 2012 | F537: =_xlfn.CONCAT(TRIM(A537)," ", ": Rating"," ",C537,","," ","Released in", " ",E537) -> The Three Stooges : Rating 5.1, Released in 2012
A538: The Oogieloves in the Big Balloon Adventure | B538: Adventure, Family, Fantasy | C538: 1.7 | D538: 15518 | E538: 2012 | F538: =_xlfn.CONCAT(TRIM(A538)," ", ": Rating"," ",C538,","," ","Released in", " ",E538) -> The Oogieloves in the Big Balloon Adventure : Rating 1.7, Released in 2012
A539: The Lords of Salem | B539: Horror, Thriller | C539: 5.2 | D539: 33002 | E539: 2012 | F539: =_xlfn.CONCAT(TRIM(A539)," ", ": Rating"," ",C539,","," ","Released in", " ",E539) -> The Lords of Salem : Rating 5.2, Released in 2012
A540: The Devil Inside | B540: Horror | C540: 4.2 | D540: 37863 | E540: 2012 | F540: =_xlfn.CONCAT(TRIM(A540)," ", ": Rating"," ",C540,","," ","Released in", " ",E540) -> The Devil Inside : Rating 4.2, Released in 2012
A541: The Cold Light of Day | B541: Action, Thriller | C541: 4.9 | D541: 40151 | E541: 2012 | F541: =_xlfn.CONCAT(TRIM(A541)," ", ": Rating"," ",C541,","," ","Released in", " ",E541) -> The Cold Light of Day : Rating 4.9, Released in 2012
A542: The Apparition | B542: Horror, Thriller | C542: 4.1 | D542: 20797 | E542: 2012 | F542: =_xlfn.CONCAT(TRIM(A542)," ", ": Rating"," ",C542,","," ","Released in", " ",E542) -> The Apparition : Rating 4.1, Released in 2012
A543: The ABCs of Death | B543: Comedy, Horror | C543: 4.7 | D543: 20720 | E543: 2012 | F543: =_xlfn.CONCAT(TRIM(A543)," ", ": Rating"," ",C543,","," ","Released in", " ",E543) -> The ABCs of Death : Rating 4.7, Released in 2012
A544: Son of Sardaar | B544: Action, Comedy, Romance | C544: 4.2 | D544: 10869 | E544: 2012 | F544: =_xlfn.CONCAT(TRIM(A544)," ", ": Rating"," ",C544,","," ","Released in", " ",E544) -> Son of Sardaar : Rating 4.2, Released in 2012
A545: So Undercover | B545: Action, Comedy, Crime | C545: 5 | D545: 21455 | E545: 2012 | F545: =_xlfn.CONCAT(TRIM(A545)," ", ": Rating"," ",C545,","," ","Released in", " ",E545) -> So Undercover : Rating 5, Released in 2012
A546: Silent Hill: Revelation | B546: Horror, Mystery, Thriller | C546: 4.9 | D546: 67763 | E546: 2012 | F546: =_xlfn.CONCAT(TRIM(A546)," ", ": Rating"," ",C546,","," ","Released in", " ",E546) -> Silent Hill: Revelation : Rating 4.9, Released in 2012
... A691: AmeriGeddon | B691: Action, Adventure, Drama | C691: 3.8 | D691: 13397 | E691: 2016 | F691: =_xlfn.CONCAT(TRIM(A691)," ", ": Rating"," ",C691,","," ","Released in", " ",E691) -> AmeriGeddon : Rating 3.8, Released in 2016
A692: 31 | B692: Horror, Thriller | C692: 5.1 | D692: 23633 | E692: 2016 | F692: =_xlfn.CONCAT(TRIM(A692)," ", ": Rating"," ",C692,","," ","Released in", " ",E692) -> 31 : Rating 5.1, Released in 2016
A693: You Get Me | B693: Crime, Drama, Mystery | C693: 4.7 | D693: 14622 | E693: 2017 | F693: =_xlfn.CONCAT(TRIM(A693)," ", ": Rating"," ",C693,","," ","Released in", " ",E693) -> You Get Me : Rating 4.7, Released in 2017
A694: xXx: Return of Xander Cage | B694: Action, Adventure, Thriller | C694: 5.2 | D694: 98457 | E694: 2017 | F694: =_xlfn.CONCAT(TRIM(A694)," ", ": Rating"," ",C694,","," ","Released in", " ",E694) -> xXx: Return of Xander Cage : Rating 5.2, Released in 2017
A695: XX | B695: Horror | C695: 4.6 | D695: 12545 | E695: 2017 | F695: =_xlfn.CONCAT(TRIM(A695)," ", ": Rating"," ",C695,","," ","Released in", " ",E695) -> XX : Rating 4.6, Released in 2017
A696: Wish Upon | B696: Drama, Fantasy, Horror | C696: 5.1 | D696: 23465 | E696: 2017 | F696: =_xlfn.CONCAT(TRIM(A696)," ", ": Rating"," ",C696,","," ","Released in", " ",E696) -> Wish Upon : Rating 5.1, Released in 2017
A697: Why We're Killing Gunther | B697: Action, Comedy, Thriller | C697: 4.8 | D697: 15608 | E697: 2017 | F697: =_xlfn.CONCAT(TRIM(A697)," ", ": Rating"," ",C697,","," ","Released in", " ",E697) -> Why We're Killing Gunther : Rating 4.8, Released in 2017
A698: Unforgettable | B698: Drama, Thriller | C698: 5.1 | D698: 16938 | E698: 2017 | F698: =_xlfn.CONCAT(TRIM(A698)," ", ": Rating"," ",C698,","," ","Released in", " ",E698) -> Unforgettable : Rating 5.1, Released in 2017
A699: Tubelight | B699: Drama, War | C699: 3.9 | D699: 22055 | E699: 2017 | F699: =_xlfn.CONCAT(TRIM(A699)," ", ": Rating"," ",C699,","," ","Released in", " ",E699) -> Tubelight : Rating 3.9, Released in 2017
A700: Transformers: The Last Knight | B700: Action, Adventure, Sci-Fi | C700: 5.2 | D700: 172818 | E700: 2017 | F700: =_xlfn.CONCAT(TRIM(A700)," ", ": Rating"," ",C700,","," ","Released in", " ",E700) -> Transformers: The Last Knight : Rating 5.2, Released in 2017
A701: The Vault | B701: Crime, Horror, Mystery | C701: 4.9 | D701: 13836 | E701: 2017 | F701: =_xlfn.CONCAT(TRIM(A701)," ", ": Rating"," ",C701,","," ","Released in", " ",E701) -> The Vault : Rating 4.9, Released in 2017
A702: The Snowman | B702: Crime, Drama, Mystery | C702: 5.2 | D702: 73530 | E702: 2017 | F702: =_xlfn.CONCAT(TRIM(A702)," ", ": Rating"," ",C702,","," ","Released in", " ",E702) -> The Snowman : Rating 5.2, Released in 2017
A703: The Layover | B703: Comedy, Romance | C703: 4.8 | D703: 17244 | E703: 2017 | F703: =_xlfn.CONCAT(TRIM(A703)," ", ": Rating"," ",C703,","," ","Released in", " ",E703) -> The Layover : Rating 4.8, Released in 2017
A704: The Humanity Bureau | B704: Sci-Fi, Thriller | C704: 4.5 | D704: 12266 | E704: 2017 | F704: =_xlfn.CONCAT(TRIM(A704)," ", ": Rating"," ",C704,","," ","Released in", " ",E704) -> The Humanity Bureau : Rating 4.5, Released in 2017
... A851: 321 Action | B851: Drama | C851: 1 | D851: 10215 | E851: 2020 | F851: =_xlfn.CONCAT(TRIM(A851)," ", ": Rating"," ",C851,","," ","Released in", " ",E851) -> 321 Action : Rating 1, Released in 2020
A852: 2067 | B852: Mystery, Sci-Fi | C852: 4.9 | D852: 12090 | E852: 2020 | F852: =_xlfn.CONCAT(TRIM(A852)," ", ": Rating"," ",C852,","," ","Released in", " ",E852) -> 2067 : Rating 4.9, Released in 2020
A853: Wolf | B853: Drama, Mystery, Thriller | C853: 5.1 | D853: 12808 | E853: 2021 | F853: =_xlfn.CONCAT(TRIM(A853)," ", ": Rating"," ",C853,","," ","Released in", " ",E853) -> Wolf : Rating 5.1, Released in 2021
A854: Thunder Force | B854: Action, Adventure, Comedy | C854: 4.6 | D854: 46282 | E854: 2021 | F854: =_xlfn.CONCAT(TRIM(A854)," ", ": Rating"," ",C854,","," ","Released in", " ",E854) -> Thunder Force : Rating 4.6, Released in 2021
A855: There's Someone Inside Your House | B855: Horror, Mystery, Thriller | C855: 4.9 | D855: 20483 | E855: 2021 | F855: =_xlfn.CONCAT(TRIM(A855)," ", ": Rating"," ",C855,","," ","Released in", " ",E855) -> There's Someone Inside Your House : Rating 4.9, Released in 2021
A856: The Unholy | B856: Drama, Horror, Mystery | C856: 5.1 | D856: 28873 | E856: 2021 | F856: =_xlfn.CONCAT(TRIM(A856)," ", ": Rating"," ",C856,","," ","Released in", " ",E856) -> The Unholy : Rating 5.1, Released in 2021
A857: The Misfits | B857: Action, Adventure, Comedy | C857: 4.5 | D857: 14124 | E857: 2021 | F857: =_xlfn.CONCAT(TRIM(A857)," ", ": Rating"," ",C857,","," ","Released in", " ",E857) -> The Misfits : Rating 4.5, Released in 2021
A858: The Kissing Booth 3 | B858: Comedy, Romance | C858: 4.8 | D858: 23297 | E858: 2021 | F858: =_xlfn.CONCAT(TRIM(A858)," ", ": Rating"," ",C858,","," ","Released in", " ",E858) -> The Kissing Booth 3 : Rating 4.8, Released in 2021
A859: The Girl on the Train | B859: Crime, Drama, Mystery | C859: 4 | D859: 15140 | E859: 2021 | F859: =_xlfn.CONCAT(TRIM(A859)," ", ": Rating"," ",C859,","," ","Released in", " ",E859) -> The Girl on the Train : Rating 4, Released in 2021
A860: The Empire | B860: Action, Drama, History | C860: 4.7 | D860: 17304 | E860: 2021 | F860: =_xlfn.CONCAT(TRIM(A860)," ", ": Rating"," ",C860,","," ","Released in", " ",E860) -> The Empire : Rating 4.7, Released in 2021
A861: The Cost of Deception | B861: Action, Crime, Drama | C861: 1.5 | D861: 40625 | E861: 2021 | F861: =_xlfn.CONCAT(TRIM(A861)," ", ": Rating"," ",C861,","," ","Released in", " ",E861) -> The Cost of Deception : Rating 1.5, Released in 2021
A862: Tandav | B862: Drama, Thriller | C862: 4.6 | D862: 61159 | E862: 2021 | F862: =_xlfn.CONCAT(TRIM(A862)," ", ": Rating"," ",C862,","," ","Released in", " ",E862) -> Tandav : Rating 4.6, Released in 2021
A863: Spiral | B863: Horror, Mystery, Thriller | C863: 5.2 | D863: 71042 | E863: 2021 | F863: =_xlfn.CONCAT(TRIM(A863)," ", ": Rating"," ",C863,","," ","Released in", " ",E863) -> Spiral : Rating 5.2, Released in 2021
A864: Space Jam: A New Legacy | B864: Adventure, Animation, Comedy | C864: 4.5 | D864: 82226 | E864: 2021 | F864: =_xlfn.CONCAT(TRIM(A864)," ", ": Rating"," ",C864,","," ","Released in", " ",E864) -> Space Jam: A New Legacy : Rating 4.5, Released in 2021
... A1001: Bad Newz | B1001: Comedy, Romance | C1001: 4.9 | D1001: 25175 | E1001: 2024 | F1001: =_xlfn.CONCAT(TRIM(A1001)," ", ": Rating"," ",C1001,","," ","Released in", " ",E1001) -> Bad Newz : Rating 4.9, Released in 2024

Sheet Chapter-7 Pivot Tables
A2: Pivot and Bar Chart -Total Votes from 2021-24 based on Genre | G2: Pie Chart to show Top 7 Vote Counts based on Genre | J2: Column Chart Top 5 Genre Having highest Votes
A3: Row Labels | B3: Sum of Total Votes In 2021 | C3: Sum of Total Votes In 2022 | D3: Sum of Total Votes In 2023 | E3: Sum of Total Votes In 2024 | G3: Row Labels | H3: Sum of Top 7 Vote Counts | J3: Sum of Highest Vote Count | K3: Column Labels
A4: Action, Adventure, Comedy | B4: 60406 | C4: 208770 | D4: 0 | E4: 31263 | G4: Action, Adventure, Comedy | H4: 1636625 | J4: Row Labels | K4: 2003 | L4: 2006 | M4: 2009 | N4: 2013 | O4: 2023 | P4: Grand Total
A5: Action, Adventure, Drama | B5: 26968 | C5: 131192 | D5: 172067 | E5: 243324 | G5: Action, Adventure, Drama | H5: 1341014 | J5: Action, Adventure, Comedy | K5: 274028 | P5: 274028
A6: Action, Adventure, Sci-Fi | B6: 0 | C6: 103225 | D6: 0 | E6: 129800 | G6: Action, Adventure, Sci-Fi | H6: 1574437 | J6: Action, Adventure, Drama | O6: 172067 | P6: 172067
A7: Adventure, Comedy, Family | B7: 0 | C7: 0 | D7: 10876 | E7: 0 | G7: Adventure, Comedy, Family | H7: 1013081 | J7: Action, Thriller | N7: 242498 | P7: 242498
A8: Comedy | B8: 0 | C8: 71074 | D8: 0 | E8: 0 | G8: Comedy | H8: 1719522 | J8: Comedy | L8: 225590 | M8: 190898 | P8: 416488
A9: Horror, Mystery, Thriller | B9: 91525 | C9: 15339 | D9: 0 | E9: 15023 | G9: Horror, Mystery, Thriller | H9: 1377044 | J9: Grand Total | K9: 274028 | L9: 225590 | M9: 190898 | N9: 242498 | O9: 172067 | P9: 1105081
A10: Horror, Thriller | B10: 0 | C10: 10942 | D10: 0 | E10: 44373 | G10: Horror, Thriller | H10: 1085481
A11: Grand Total | B11: 178899 | C11: 540542 | D11: 182943 | E11: 463783 | G11: Grand Total | H11: 9747204

Sheet Chapter -8
A2: Projected Profitability and Break-Even Analysis
A4: Assumptions: | F4: Projections:
K5: Year Wise Break Even on Tickets Sold and If Ticket Price Increases by 2 or More Percent
A6: Revenue | K6: Year | L6: Ticket Sold | M6: Ticket Price | N6: Total Revenue | O6: Variable Expenses | P6: Fixed Expenses | Q6: Net Profit ($) | R6: Break-Even Tickets Sold
B7: Ticket Sold Per Year | C7: 444550 | F7: Sales Revenue | I7: =C7*C8 -> 6668250 | K7: 2024 | L7: 1065820 | M7: =10*1.02^0 -> 10 | N7: =L7*M7 -> 10658200 | O7: =N7*0.23 -> 2451386 | P7: 2250000 | Q7: =N7-(O7+P7) -> 5956814 | R7: =ROUND(P7/(M7-(O7/L7)),0) -> 292208
B8: Per ticket price | C8: 15 | F8: Variable Costs: | K8: 2025 | L8: 1118111 | M8: =10*1.02^1 -> 10.2 | N8: =ROUND((L8*M8),0) -> 11404732 | O8: =ROUND((N8*0.23),0) -> 2623088 | P8: 2295000 | Q8: =N8-(O8+P8) -> 6486644 | R8: =ROUND(P8/(M8-(O8/L8)),0) -> 292208
A9: Variable Cost Per Unit | F9: Marketing | H9: =C7*C10 -> 889100 | K9: 2026 | L9: 1173016 | M9: =ROUND((10*1.02^2),1) -> 10.4 | N9: =ROUND((L9*M9),0) -> 12199366 | O9: =ROUND((N9*0.23),0) -> 2805854 | P9: 2340900 | Q9: =N9-(O9+P9) -> 7052612 | R9: =ROUND(P9/(M9-(O9/L9)),0) -> 292320
B10: Marketing Expenses | C10: 2 | F10: Distribution | H10: =C7*C11 -> 644597.5 | K10: 2027 | L10: 1230667 | M10: =ROUND((10*1.02^3),1) -> 10.6 | N10: =ROUND((L10*M10),0) -> 13045070 | O10: =ROUND((N10*0.23),0) -> 3000366 | P10: 2387718 | Q10: =N10-(O10+P10) -> 7656986 | R10: =ROUND(P10/(M10-(O10/L10)),0) -> 292541
B11: Distribution Expenses | C11: 1.45 | F11: Total Variable Costs | I11: =H9+H10 -> 1533697.5 | K11: 2028 | L11: 1291200 | M11: =ROUND((10*1.02^4),1) -> 10.8 | N11: =L11*M11 -> 13944960 | O11: =ROUND((N11*0.23),0) -> 3207341 | P11: 2435472 | Q11: =N11-(O11+P11) -> 8302147 | R11: =ROUND(P11/(M11-(O11/L11)),0) -> 292866
A12: Fixed Costs | F12: Contribution margin | I12: =I7-I11 -> 5134552.5 | K12: 2029 | L12: 444550 | M12: 15 | N12: =L12*M12 -> 6668250 | O12: =ROUND((N12*0.23),0) -> 1533698 | P12: 2483226 | Q12: =N12-(O12+P12) -> 2651326 | R12: =ROUND(P12/(M12-(O12/L12)),0) -> 214998 | S12: Break even Point
B13: Salaries | C13: 683226 | F13: Fixed Costs:
B14: Technology Investment | C14: 800000 | F14: Salaries | H14: =C13 -> 683226 | L14: Variable Expenses = Total Revenue×0.23 -This means for every dollar of revenue, 23 cents are spent on variable expenses Revenue Growth: Total revenue increases each year due to a combination of higher ticket sales and a price increase in 2027. Expenses: Both variable and fixed expenses rise over the years, likely due to inflation, higher costs, or expanding operations. Net Profit Growth: The net profit shows consistent growth each year, from $5,956,814 in 2024 to $8,302,147 in 2028. This suggests effective cost management and increasing ticket demand. Break-Even Stability: The stability of the break-even point is generally strong from 2024 to 2028, with a relatively small increase in the break-even number of tickets each year.
B15: Advertising | C15: 1000000 | F15: Technology Investment | H15: =C14 -> 800000
F16: Advertising | H16: =C15 -> 1000000
F17: Total Fixed Costs | I17: =H14+H15+H16 -> 2483226
F18: Profit Before Taxes | I18: =I12-I17 -> 2651326.5
L22: 2029 stands out as a year of significant change in both ticket prices and break-even tickets. The increase in ticket price to $15.00 substantially reduced the break-even number of tickets, but the lower number of tickets sold compared to previous years (444,550) could present challenges to meeting the expected revenue goals. Overall, the break-even point is stable, but there are some risks in 2029 with lower ticket sales despite the higher price. This indicates potential volatility or a shift in market conditions.

Sheet Chapter-9
A1: Movie Theater Revenue Analysis
A2: 2023 Income Statement Analysis
A3: Category | B3: Projected
A4: Ticket Sold Per Year | B4: 1065820
A5: Per ticket price | B5: 10
A6: Total Revenue | B6: =B4*B5 -> 10658200
A8: Variable Expenses
A9: Category | B9: Projected | G9: Results Summary
A10: Marketing Expenses (10%) | B10: =B6*10% -> 1065820 | D10: Break-Even Analysis | G10: Metric | H10: Value
A11: Distribution Expenses (5%) | B11: =B6*5% -> 532910 | D11: Category | E11: Projected | G11: Total Revenue | H11: 10658200
A12: Royalties (8%) | B12: =B6*8% -> 852656 | D12: Fixed Expenses | E12: =B21 -> 2250000 | G12: Total Variable Expenses | H12: 2451386
A13: Total Variable Expenses | B13: =SUM(B10:B12) -> 2451386 | D13: Variable Cost per Ticket | E13: =B13/B4 -> 2.3 | G13: Total Fixed Expenses | H13: 2250000
D14: Average Ticket Price | E14: 10 | G14: Net Profit | H14: 5956814
A15: Fixed Expenses | D15: Break-Even Tickets Sold | E15: =ROUND(B21/(B5-E13),0) -> 292208 | G15: Break-Even Tickets | H15: 292208
A16: Category | B16: Projected
A17: Studio Overhead | B17: 500000
A18: Salaries | B18: 1000000
A19: Technology Investment | B19: 300000
A20: Advertising | B20: 450000
A21: Total Fixed Expenses | B21: =SUM(B17:B20) -> 2250000
A23: Summary
A24: Category | B24: Projected
A25: Total Revenue | B25: =$B6 -> 10658200
A26: Total Variable Expenses | B26: =B13 -> 2451386
A27: Total Fixed Expenses | B27: =B21 -> 2250000
A28: Net Profit (or Loss) | B28: =B6-B13-B21 -> 5956814
